Workbook

Sheet Recommended_CEM_Base
A1: Recommended ERCOT CEM Base — Technology-Specific Sources (Real 2025$)
A2: Recommended hybrid base: ERCOT LTSA for gas / ICE / SMR / solar and 2h/6h storage; ATB Moderate Class 1 for wind; NLR 2025 Mid for 4-hour battery CAPEX; plus two separate diesel applications: backup generator and utility-scale peaker plant.
A3: Technology | B3: Economic life (yr) | C3: Real WACC | D3: 2030 CAPEX (2025$/kW) | E3: CRF | F3: 2030 annualized CAPEX (2025$/kW-yr) | G3: 2030 FOM (2025$/kW-yr) | H3: 2030 total fixed (2025$/kW-yr) | I3: VOM (2025$/MWh) | J3: Heat rate (Btu/kWh) | K3: 2035 CAPEX (2025$/kW) | L3: 2035 annualized CAPEX (2025$/kW-yr) | M3: 2035 FOM (2025$/kW-yr) | N3: 2035 total fixed (2025$/kW-yr) | O3: CAPEX source | P3: O&M source | Q3: Modeling note
A4: CC multi-shaft | B4: =Assumptions!B15 -> 30 | C4: =Assumptions!$B$5 -> 0.07 | D4: =ERCOT_LTSA_2026!B30 -> 1314.8599 | E4: =C4*(1+C4)^B4/((1+C4)^B4-1) -> 0.080586404 | F4: =D4*E4 -> 105.95983 | G4: =EIA_AEO2026_TRE!H6 -> 12.69 | H4: =F4+IF(G4="",0,G4) -> 118.64983 | I4: =EIA_AEO2026_TRE!I6 -> 3.57 | J4: =EIA_AEO2026_TRE!J6 -> 6226 | K4: =ERCOT_LTSA_2026!B35 -> 1254.1144 | L4: =K4*E4 -> 101.06457 | M4: =EIA_AEO2026_TRE!H6 -> 12.69 | N4: =L4+IF(M4="",0,M4) -> 113.75457 | O4: ERCOT 2026 LTSA | P4: EIA AEO2026; held constant in real 2025$ unless changed | Q4: Recommended base = ERCOT LTSA CAPEX; EIA TRE is a lower current regional anchor, not a 2030/2035 forecast.
A5: Advanced CT | B5: =Assumptions!B16 -> 30 | C5: =Assumptions!$B$5 -> 0.07 | D5: =ERCOT_LTSA_2026!C30 -> 1193.778 | E5: =C5*(1+C5)^B5/((1+C5)^B5-1) -> 0.080586404 | F5: =D5*E5 -> 96.202277 | G5: =EIA_AEO2026_TRE!H9 -> 7.18 | H5: =F5+IF(G5="",0,G5) -> 103.38228 | I5: =EIA_AEO2026_TRE!I9 -> 4.17 | J5: =EIA_AEO2026_TRE!J9 -> 9142 | K5: =ERCOT_LTSA_2026!C35 -> 1109.3161 | L5: =K5*E5 -> 89.395793 | M5: =EIA_AEO2026_TRE!H9 -> 7.18 | N5: =L5+IF(M5="",0,M5) -> 96.575793 | O5: ERCOT 2026 LTSA | P5: EIA AEO2026; held constant in real 2025$ unless changed | Q5: Recommended base = ERCOT LTSA CAPEX; EIA industrial-frame CT provides the current Texas regional anchor.
A6: ICE | B6: =Assumptions!B17 -> 30 | C6: =Assumptions!$B$5 -> 0.07 | D6: =ERCOT_LTSA_2026!D30 -> 2102.3408 | E6: =C6*(1+C6)^B6/((1+C6)^B6-1) -> 0.080586404 | F6: =D6*E6 -> 169.42009 | H6: =F6+IF(G6="",0,G6) -> 169.42009 | K6: =ERCOT_LTSA_2026!D35 -> 2036.8298 | L6: =K6*E6 -> 164.14079 | N6: =L6+IF(M6="",0,M6) -> 164.14079 | O6: ERCOT 2026 LTSA | P6: Not populated — add engine-specific O&M/performance source | Q6: ICE = reciprocating internal-combustion engine. Keep optional unless flexible engine capacity is explicitly represented; engine-specific O&M/heat rate still needed.
A7: SMR | B7: =Assumptions!B18 -> 60 | C7: =Assumptions!$B$5 -> 0.07 | D7: =ERCOT_LTSA_2026!E30 -> 8608.4759 | E7: =C7*(1+C7)^B7/((1+C7)^B7-1) -> 0.071229226 | F7: =D7*E7 -> 613.17507 | G7: =EIA_AEO2026_TRE!H11 -> 127.62 | H7: =F7+IF(G7="",0,G7) -> 740.79507 | I7: =EIA_AEO2026_TRE!I11 -> 3.32 | J7: =EIA_AEO2026_TRE!J11 -> 10445 | K7: =ERCOT_LTSA_2026!E35 -> 8133.6439 | L7: =K7*E7 -> 579.35315 | M7: =EIA_AEO2026_TRE!H11 -> 127.62 | N7: =L7+IF(M7="",0,M7) -> 706.97315 | O7: ERCOT 2026 LTSA | P7: EIA AEO2026; held constant in real 2025$ unless changed | Q7: Recommended central SMR CAPEX = ERCOT LTSA, but cost uncertainty is very large; retain ATB Advanced and Conservative cases as explicit low/high sensitivities.
A8: Wind | B8: =Assumptions!B19 -> 30 | C8: =Assumptions!$B$5 -> 0.07 | D8: =NLR_ATB_2024b!K15 -> 1548.8568 | E8: =C8*(1+C8)^B8/((1+C8)^B8-1) -> 0.080586404 | F8: =D8*E8 -> 124.8168 | G8: =NLR_ATB_2024b!M15 -> 32.1924 | H8: =F8+G8 -> 157.0092 | I8: =NLR_ATB_2024b!O15 -> 0 | K8: =NLR_ATB_2024b!L15 -> 1468.2638 | L8: =K8*E8 -> 118.3221 | M8: =NLR_ATB_2024b!N15 -> 31.089513 | N8: =L8+M8 -> 149.41161 | O8: NLR/NREL ATB 2024b Moderate — Wind Class 1 | P8: NLR/NREL ATB 2024b Moderate | Q8: Recommended base uses ATB Moderate Class 1 because ERCOT LTSA wind CAPEX is materially above ATB and recent ERCOT LBNL actuals; ERCOT LTSA is retained as a conservative/high benchmark.
A9: Solar | B9: =Assumptions!B20 -> 30 | C9: =Assumptions!$B$5 -> 0.07 | D9: =ERCOT_LTSA_2026!G30 -> 1171.3554 | E9: =C9*(1+C9)^B9/((1+C9)^B9-1) -> 0.080586404 | F9: =D9*E9 -> 94.395322 | G9: =EIA_AEO2026_TRE!H14 -> 23.6 | H9: =F9+IF(G9="",0,G9) -> 117.99532 | I9: =EIA_AEO2026_TRE!I14 -> 0 | K9: =ERCOT_LTSA_2026!G35 -> 1052.2012 | L9: =K9*E9 -> 84.793109 | M9: =EIA_AEO2026_TRE!H14 -> 23.6 | N9: =L9+IF(M9="",0,M9) -> 108.39311 | O9: ERCOT 2026 LTSA | P9: EIA AEO2026; held constant in real 2025$ unless changed | Q9: Recommended base = ERCOT LTSA solar CAPEX; ATB/EIA are relatively close and remain useful sensitivities/checks.
A10: BESS 2h | B10: =Assumptions!B21 -> 15 | C10: =Assumptions!$B$5 -> 0.07 | D10: =ERCOT_LTSA_2026!H30 -> 697.79061 | E10: =C10*(1+C10)^B10/((1+C10)^B10-1) -> 0.10979462 | F10: =D10*E10 -> 76.613658 | G10: =NLR_ATB_2024b!M24 -> 22.242684 | H10: =F10+IF(G10="",0,G10) -> 98.856342 | I10: =NLR_ATB_2024b!O24 -> 0 | K10: =ERCOT_LTSA_2026!H35 -> 645.15699 | L10: =K10*E10 -> 70.83477 | M10: =NLR_ATB_2024b!N24 -> 20.713591 | N10: =L10+IF(M10="",0,M10) -> 91.548361 | O10: ERCOT 2026 LTSA | P10: NLR/NREL ATB Moderate duration-specific O&M | Q10: 2-hour BESS remains an alternate-duration option; recommended CAPEX = ERCOT LTSA because the newer NLR 2025 projection is specifically used here for 4-hour storage.
A11: BESS 4h | B11: =Assumptions!B22 -> 15 | C11: =Assumptions!$B$5 -> 0.07 | D11: =NLR_BESS_2025!I11 -> 1145.365 | E11: =C11*(1+C11)^B11/((1+C11)^B11-1) -> 0.10979462 | F11: =D11*E11 -> 125.75492 | G11: =NLR_ATB_2024b!M27 -> 35.756699 | H11: =F11+G11 -> 161.51161 | I11: =NLR_ATB_2024b!O27 -> 0 | K11: =NLR_BESS_2025!I16 -> 997.57593 | L11: =K11*E11 -> 109.52847 | M11: =NLR_ATB_2024b!N27 -> 32.999473 | N11: =L11+M11 -> 142.52795 | O11: NLR 2025 Utility-Scale Battery Storage — Mid | P11: NLR/NREL ATB 2024b Moderate duration-specific O&M | Q11: Recommended 4-hour BESS CAPEX uses the newer NLR 2025 Mid trajectory; use NLR Low/High as the preferred battery cost sensitivities.
A12: BESS 6h | B12: =Assumptions!B23 -> 15 | C12: =Assumptions!$B$5 -> 0.07 | D12: =ERCOT_LTSA_2026!J30 -> 1705.0128 | E12: =C12*(1+C12)^B12/((1+C12)^B12-1) -> 0.10979462 | F12: =D12*E12 -> 187.20124 | G12: =NLR_ATB_2024b!M30 -> 49.270714 | H12: =F12+IF(G12="",0,G12) -> 236.47195 | I12: =NLR_ATB_2024b!O30 -> 0 | K12: =ERCOT_LTSA_2026!J35 -> 1576.6929 | L12: =K12*E12 -> 173.11241 | M12: =NLR_ATB_2024b!N30 -> 45.285354 | N12: =L12+IF(M12="",0,M12) -> 218.39776 | O12: ERCOT 2026 LTSA | P12: NLR/NREL ATB Moderate duration-specific O&M | Q12: 6-hour BESS remains an alternate-duration option; recommended CAPEX = ERCOT LTSA because the newer NLR 2025 projection is specifically used here for 4-hour storage.
A13: Diesel backup generator | B13: =Assumptions!B24 -> 20 | C13: =Assumptions!$B$5 -> 0.07 | D13: =Diesel_Review!B20 -> 800 | E13: =C13*(1+C13)^B13/((1+C13)^B13-1) -> 0.094392926 | F13: =D13*E13 -> 75.514341 | G13: =Diesel_Review!D20 -> 35 | H13: =F13+G13 -> 110.51434 | I13: =Diesel_Review!E20 -> 0 | J13: =Diesel_Review!F20*1000 -> 9500 | K13: =Diesel_Review!C20 -> 800 | L13: =K13*E13 -> 75.514341 | M13: =Diesel_Review!D20 -> 35 | N13: =L13+M13 -> 110.51434 | O13: Backup-generator synthesis (NREL / EDF / BofA / MIT) | P13: EDF 2024 non-fuel annual operating-cost benchmark | Q13: Standby/resilience generator. Recommended CAPEX is $800/kW in real 2025$ for both 2030 and 2035; do not use this row as the utility-scale peaker assumption.
A14: Diesel peaker plant | B14: 30 | C14: 0.07 | D14: 1373.9 | E14: 0.1 | F14: 110.7 | G14: 44.3 | H14: 155 | I14: 7.2 | J14: 9500 | K14: 1373.9 | L14: 110.7 | M14: 44.3 | N14: 155 | O14: EIA/S&L AEO2020 Texas 20-MW ICE plant | P14: EIA/S&L engine-plant O&M proxy | Q14: Utility-scale/grid-connected peaker. CAPEX = EIA Texas-Houston location-adjusted 20-MW internal-combustion-engine benchmark converted to 2025$. Kept separate from the $800/kW backup-generator case.
A15: Diesel peaker plant | B15: =Assumptions!B25 -> 30 | C15: =Assumptions!$B$5 -> 0.07 | D15: =Diesel_Review!B21 -> 1373.8713 | E15: =C15*(1+C15)^B15/((1+C15)^B15-1) -> 0.080586404 | F15: =D15*E15 -> 110.71535 | G15: =Diesel_Review!D21 -> 44.276182 | H15: =F15+G15 -> 154.99153 | I15: =Diesel_Review!E21 -> 7.1652866 | J15: =Diesel_Review!F21*1000 -> 9500 | K15: =Diesel_Review!C21 -> 1373.8713 | L15: =K15*E15 -> 110.71535 | M15: =Diesel_Review!D21 -> 44.276182 | N15: =L15+M15 -> 154.99153 | O15: EIA/S&L AEO2020 Texas 20-MW ICE plant | P15: EIA/S&L engine-plant O&M proxy | Q15: Utility-scale/grid-connected peaker. CAPEX = EIA Texas-Houston location-adjusted 20-MW internal-combustion-engine benchmark converted to 2025$. Kept separate from the $800/kW backup-generator case.
A17: Annualization method
A18: CRF = r(1+r)^n / [(1+r)^n - 1]. Annualized CAPEX = real-2025$ CAPEX × CRF. Total fixed = annualized CAPEX + FOM.
A19: The 7% real WACC and economic lives are editable assumptions on the Assumptions sheet; they are not source facts.
A20: For direct CEM import, the 2030 columns D/F/G/H/I/J and 2035 columns K/L/M/N are the main outputs.
A22: Recommended CAPEX Sensitivity Anchors — Real 2025$/kW
A23: Technology | B23: 2030 Low | C23: 2030 Base | D23: 2030 High | E23: 2035 Low | F23: 2035 Base | G23: 2035 High | H23: Guidance
A24: SMR | B24: =NLR_ATB_2024b!K11 -> 7058.9076 | C24: =D7 -> 8608.4759 | D24: =NLR_ATB_2024b!K13 -> 13950.214 | E24: =NLR_ATB_2024b!L11 -> 4222.7394 | F24: =K7 -> 8133.6439 | G24: =NLR_ATB_2024b!L13 -> 13259.61 | H24: Low = ATB Advanced; Base = ERCOT LTSA; High = ATB Conservative. Treat as a wide scenario range, not a tight confidence interval.
A25: Wind | B25: =NLR_ATB_2024b!K14 -> 1475.9427 | C25: =D8 -> 1548.8568 | D25: =CEM_BaseCase!D8 -> 2010.8567 | E25: =NLR_ATB_2024b!L14 -> 1384.776 | F25: =K8 -> 1468.2638 | G25: =CEM_BaseCase!K8 -> 1960.4085 | H25: Low = ATB Advanced Class 1; Base = ATB Moderate Class 1; High = ERCOT LTSA planning assumption. LBNL ERCOT actual cost remains an empirical calibration.
A26: BESS 4h | B26: =NLR_BESS_2025!H11 -> 849.7869 | C26: =D11 -> 1145.365 | D26: =NLR_BESS_2025!J11 -> 1453.2588 | E26: =NLR_BESS_2025!H16 -> 603.47186 | F26: =K11 -> 997.57593 | G26: =NLR_BESS_2025!J16 -> 1391.68 | H26: Low/Base/High = NLR 2025 Low/Mid/High trajectories; this is the preferred storage cost sensitivity family.
A27: Diesel backup generator | B27: =Diesel_Review!I20 -> 600 | C27: =Diesel_Review!J20 -> 800 | D27: =Diesel_Review!K20 -> 1000 | E27: =Diesel_Review!I20 -> 600 | F27: =Diesel_Review!J20 -> 800 | G27: =Diesel_Review!K20 -> 1000 | H27: Low/Base/High = $600/$800/$1,000 per kW in real 2025$ for a standby/resilience generator; held flat in real terms.
A28: Diesel peaker plant | B28: =Diesel_Review!I21 -> 1094.0493 | C28: =Diesel_Review!J21 -> 1373.8713 | D28: =Diesel_Review!K21 -> 1717.3391 | E28: =Diesel_Review!I21 -> 1094.0493 | F28: =Diesel_Review!J21 -> 1373.8713 | G28: =Diesel_Review!K21 -> 1717.3391 | H28: Low = EIA 2024 observed petroleum-liquids cost; Base = EIA Texas 20-MW ICE engineering benchmark; High = 25% stress case above base. Held flat in real terms.

Sheet Assumptions
A1: ERCOT CEM Technology-Cost Workbook — Conversion & Annualization Assumptions
A3: Assumption | B3: Value | C3: Unit | D3: Use | E3: Editable? | F3: Source / note
A4: ERCOT LTSA nominal inflation | B4: 0.022 | C4: %/yr | D4: Deflate ERCOT future nominal costs back to 2025$ | E4: Yes | F4: ERCOT 2026 LTSA
A5: Real discount rate / WACC | B5: 0.07 | C5: % | D5: Annualize CAPEX with a capital recovery factor | E5: Yes | F5: Modeling default — change to your CEM convention
A6: Base dollar year | B6: 2025 | C6: year | D6: Common comparison dollar year | E6: Yes | F6: User requested 2025$
A8: Dollar year | B8: CPI-U annual average | C8: 2025$/source-$ factor | D8: Source URL
A9: 2022 | B9: 292.655 | C9: =$B$12/B9 -> 1.1000769 | D9: https://www.bls.gov/regions/northeast/data/consumerpriceindex_us_table.htm
A10: 2023 | B10: 304.702 | C10: =$B$12/B10 -> 1.0565832 | D10: https://www.bls.gov/regions/northeast/data/consumerpriceindex_us_table.htm
A11: 2024 | B11: 313.689 | C11: =$B$12/B11 -> 1.0263127 | D11: https://www.bls.gov/regions/northeast/data/consumerpriceindex_us_table.htm
A12: 2025 | B12: 321.943 | C12: =$B$12/B12 -> 1 | D12: https://www.bls.gov/regions/northeast/data/consumerpriceindex_us_table.htm
A14: Technology | B14: Economic life (yr) | C14: Note
A15: CC multi-shaft | B15: 30 | C15: Editable CEM annualization assumption
A16: Advanced CT | B16: 30 | C16: Editable CEM annualization assumption
A17: ICE | B17: 30 | C17: Editable CEM annualization assumption
A18: SMR | B18: 60 | C18: Editable CEM annualization assumption
A19: Wind | B19: 30 | C19: Editable CEM annualization assumption
A20: Solar | B20: 30 | C20: Editable CEM annualization assumption
A21: BESS 2h | B21: 15 | C21: Editable CEM annualization assumption
A22: BESS 4h | B22: 15 | C22: Editable CEM annualization assumption
A23: BESS 6h | B23: 15 | C23: Editable CEM annualization assumption
A24: Diesel backup generator | B24: 20 | C24: NREL backup-generator useful life; editable CEM annualization assumption
A25: Diesel peaker plant | B25: 30 | C25: EIA utility-scale internal-combustion-engine operating life; editable CEM annualization assumption
A27: Conversion methodology
A28: 2022/2023/2024 source-dollar values are converted to 2025$ using annual-average U.S. CPI-U ratios.
A29: Conversion methodology
A30: 2022/2023/2024 source-dollar values are converted to 2025$ using annual-average U.S. CPI-U ratios.

Sheet README_Sources
A1: ERCOT Capacity-Expansion Technology Cost Assumptions — 2030 / 2035
A3: Source | B3: Role in workbook | C3: Geography | D3: Dollar basis | E3: Projection status | F3: Why useful for ERCOT | G3: URL
A4: ERCOT 2026 LTSA — Current Trends | B4: Primary base CAPEX | C4: ERCOT | D4: Nominal future $; converted to 2025$ | E4: 2027–2041 annual series | F4: ERCOT's own CEM/planning assumptions | G4: https://www.ercot.com/files/docs/2025/12/15/2026-LTSA-Update-Current-Trends-Capacity-Expansion-Results.pdf
A5: EIA AEO2026 Electricity Market Module | B5: Regional cost/O&M benchmark | C5: TRE = Texas | D5: 2025$ | E5: Initial/current new-build cost anchor | F5: Texas regional multipliers + updated gas turbine costs | G5: https://www.eia.gov/outlooks/aeo/assumptions/pdf/EMM_Assumptions.pdf
A6: NLR/NREL 2024b ATB v4 | B6: Technology-learning sensitivity | C6: U.S. / resource classes | D6: 2022$ | E6: 2030/2035 Advanced / Moderate / Conservative | F6: Transparent long-run technology learning cases | G6: https://data.openei.org/files/6006/2024_v4_Workbook_7-22-2026.xlsx
A7: NLR Utility-Scale Battery Storage 2025 Update | B7: Battery-specific sensitivity | C7: U.S. | D7: 2024$ | E7: Annual future projections | F7: More current storage learning than frozen 2024 ATB | G7: https://www.nlr.gov/docs/fy25osti/93281.pdf
A8: Berkeley Lab Land-Based Wind Market Report 2024 | B8: Empirical calibration | C8: ERCOT | D8: 2023$ | E8: Historical actual 2022–2023 projects | F8: Direct ERCOT observed project-cost benchmark | G8: https://emp.lbl.gov/sites/default/files/2024-08/Land-Based%20Wind%20Market%20Report_2024%20Edition.pdf
A9: Berkeley Lab Utility-Scale Solar 2025 | B9: Empirical calibration | C9: U.S. | D9: 2024$ | E9: Historical actual 2024 projects | F9: Observed utility-scale PV benchmark; not ERCOT-specific | G9: https://emp.lbl.gov/publications/us-utility-scale-solar-2025-data
A10: BLS CPI-U | B10: Dollar-year conversion | C10: U.S. | D10: Index | E10: Historical | F10: Transparent conversion to 2025 dollars | G10: https://www.bls.gov/regions/northeast/data/consumerpriceindex_us_table.htm
A11: Lazard LCOE+ v18 | B11: Underlying/secondary benchmark | C11: U.S. | D11: Varies | E11: Market benchmark | F11: Cited by ERCOT LTSA as an input source; not separately harmonized | G11: https://www.lazard.com/research-insights/levelized-cost-of-energyplus/
A12: Diesel technology review | B12: Backup-generator + utility-scale peaker benchmark | C12: U.S.; Texas-specific engineering benchmark for peaker | D12: Mixed source years normalized to 2025$ | E12: Mature technology; flat-real-cost base assumption | F12: Separates standby backup generator from a grid-connected liquid-fuel peaker; detailed reconciliation is in Diesel_Review. | G12: https://www.eia.gov/analysis/studies/powerplants/capitalcost/pdf/capital_cost_AEO2020.pdf
A13: Recommended interpretation
A14: Base case | B14: Use the technology-specific hybrid in Recommended_CEM_Base: ERCOT LTSA for gas/ICE/SMR/solar and 2h/6h BESS; ATB Moderate Class 1 for wind; NLR 2025 Mid for 4h BESS; $800/kW backup diesel for standby use; and the EIA Texas utility-scale ICE benchmark for diesel peaker.
A15: Cross-check | B15: Use EIA TRE/Texas as a current regional anchor; do not relabel it as an explicit 2030/2035 forecast.
A16: Learning sensitivities | B16: Wind: ATB Advanced / Moderate with ERCOT LTSA as conservative planning benchmark. 4h BESS: NLR 2025 Low/Mid/High. SMR: ATB Advanced / ERCOT / ATB Conservative.
A17: Empirical calibration | B17: Use LBNL actual wind/solar costs as a reality check, not as forward projections.
A18: Annualization | B18: Recommended_CEM_Base applies the editable real WACC/life and then adds FOM; HOPE_CostProfiles converts the recommended fixed cost to $/MW-yr.
A19: Workbook navigation | B19: Recommended_CEM_Base = preferred hybrid inputs; CEM_BaseCase = all-ERCOT-LTSA benchmark; HOPE_CostProfiles = HOPE-formatted recommended costs.
A20: HOPE model-input format references (from current GitHub project)
A21: HOPE candidate cost profile | B21: candidate_resource_costs_2035.csv | C21: Current HOPE project format | D21: Stores CAPEX/FOM/FCR plus final $/MW-yr and $/MWh | E21: Used by the case builder | F21: HOPE_CostProfiles follows this schema in columns A:U | G21: https://github.com/swang22/PJM_DC_health_study_project/blob/main/scenario_assumptions/candidate_resource_costs_2035.csv
A22: HOPE generation candidates | B22: gendata_candidate.csv | C22: Current HOPE project format | D22: Direct model input | E22: Project/zone/build limit + fixed/variable cost + reliability/emissions | F22: HOPE_GenCandidate follows the exact model columns in A:Y | G22: https://github.com/swang22/PJM_DC_health_study_project/blob/main/ModelCases/PJM_ICARUS21_GTEP_2035_Base_case/Data_PJM_ICARUS21_GTEP_2035_Base/gendata_candidate.csv
A23: HOPE storage candidates | B23: storagedata_candidate.csv | C23: Current HOPE project format | D23: Direct model input | E23: Energy/power capacity + efficiency + fixed/variable cost + CC | F23: HOPE_StorageCandidate follows the exact model columns in A:V | G23: https://github.com/swang22/PJM_DC_health_study_project/blob/main/ModelCases/PJM_ICARUS21_GTEP_2035_Base_case/Data_PJM_ICARUS21_GTEP_2035_Base/storagedata_candidate.csv

Sheet ERCOT_LTSA_2026
A1: ERCOT 2026 LTSA — New Unit Capital Costs
A2: Source: | B2: https://www.ercot.com/files/docs/2025/12/15/2026-LTSA-Update-Current-Trends-Capacity-Expansion-Results.pdf
A4: Raw source values — nominal $/kW
A5: Year | B5: CC multi-shaft | C5: Advanced CT | D5: ICE | E5: SMR | F5: Wind | G5: Solar | H5: BESS 2h | I5: BESS 4h | J5: BESS 6h
B6: nominal $/kW | C6: nominal $/kW | D6: nominal $/kW | E6: nominal $/kW | F6: nominal $/kW | G6: nominal $/kW | H6: nominal $/kW | I6: nominal $/kW | J6: nominal $/kW
A7: 2027 | B7: 1436 | C7: 1325 | D7: 2236 | E7: 9439 | F7: 2165 | G7: 1308 | H7: 782 | I7: 1347 | J7: 1912
A8: 2028 | B8: 1439 | C8: 1319 | D8: 2272 | E8: 9450 | F8: 2180 | G8: 1289 | H8: 770 | I8: 1326 | J8: 1882
A9: 2029 | B9: 1449 | C9: 1321 | D9: 2308 | E9: 9509 | F9: 2207 | G9: 1296 | H9: 772 | I9: 1329 | J9: 1887
A10: 2030 | B10: 1466 | C10: 1331 | D10: 2344 | E10: 9598 | F10: 2242 | G10: 1306 | H10: 778 | I10: 1339 | J10: 1901
A11: 2031 | B11: 1487 | C11: 1344 | D11: 2379 | E11: 9716 | F11: 2284 | G11: 1307 | H11: 786 | I11: 1352 | J11: 1920
A12: 2032 | B12: 1508 | C12: 1357 | D12: 2417 | E12: 9831 | F12: 2325 | G12: 1311 | H12: 789 | I12: 1359 | J12: 1929
A13: 2033 | B13: 1529 | C13: 1369 | D13: 2456 | E13: 9938 | F13: 2365 | G13: 1313 | H13: 795 | I13: 1368 | J13: 1942
A14: 2034 | B14: 1540 | C14: 1364 | D14: 2494 | E14: 10033 | F14: 2403 | G14: 1312 | H14: 798 | I14: 1374 | J14: 1950
A15: 2035 | B15: 1559 | C15: 1379 | D15: 2532 | E15: 10111 | F15: 2437 | G15: 1308 | H15: 802 | I15: 1381 | J15: 1960
A16: 2036 | B16: 1581 | C16: 1395 | D16: 2568 | E16: 10201 | F16: 2475 | G16: 1308 | H16: 806 | I16: 1387 | J16: 1969
A17: 2037 | B17: 1606 | C17: 1415 | D17: 2606 | E17: 10311 | F17: 2518 | G17: 1317 | H17: 810 | I17: 1394 | J17: 1979
A18: 2038 | B18: 1633 | C18: 1437 | D18: 2645 | E18: 10425 | F18: 2563 | G18: 1328 | H18: 814 | I18: 1402 | J18: 1990
... A21: 2041 | B21: 1714 | C21: 1502 | D21: 2766 | E21: 10760 | F21: 2700 | G21: 1376 | H21: 829 | I21: 1428 | J21: 2027
A24: Converted values — real 2025$/kW
A25: Year | B25: CC multi-shaft | C25: Advanced CT | D25: ICE | E25: SMR | F25: Wind | G25: Solar | H25: BESS 2h | I25: BESS 4h | J25: BESS 6h
B26: 2025$/kW | C26: 2025$/kW | D26: 2025$/kW | E26: 2025$/kW | F26: 2025$/kW | G26: 2025$/kW | H26: 2025$/kW | I26: 2025$/kW | J26: 2025$/kW
A27: =A7 -> 2027 | B27: =B7/(1+Assumptions!$B$4)^(A27-Assumptions!$B$6) -> 1374.8415 | C27: =C7/(1+Assumptions!$B$4)^(A27-Assumptions!$B$6) -> 1268.569 | D27: =D7/(1+Assumptions!$B$4)^(A27-Assumptions!$B$6) -> 2140.77 | E27: =E7/(1+Assumptions!$B$4)^(A27-Assumptions!$B$6) -> 9036.9982 | F27: =F7/(1+Assumptions!$B$4)^(A27-Assumptions!$B$6) -> 2072.7938 | G27: =G7/(1+Assumptions!$B$4)^(A27-Assumptions!$B$6) -> 1252.293 | H27: =H7/(1+Assumptions!$B$4)^(A27-Assumptions!$B$6) -> 748.69505 | I27: =I7/(1+Assumptions!$B$4)^(A27-Assumptions!$B$6) -> 1289.632 | J27: =J7/(1+Assumptions!$B$4)^(A27-Assumptions!$B$6) -> 1830.569
A28: =A8 -> 2028 | B28: =B8/(1+Assumptions!$B$4)^(A28-Assumptions!$B$6) -> 1348.0565 | C28: =C8/(1+Assumptions!$B$4)^(A28-Assumptions!$B$6) -> 1235.6404 | D28: =D8/(1+Assumptions!$B$4)^(A28-Assumptions!$B$6) -> 2128.4117 | E28: =E8/(1+Assumptions!$B$4)^(A28-Assumptions!$B$6) -> 8852.7688 | F28: =F8/(1+Assumptions!$B$4)^(A28-Assumptions!$B$6) -> 2042.226 | G28: =G8/(1+Assumptions!$B$4)^(A28-Assumptions!$B$6) -> 1207.5364 | H28: =H8/(1+Assumptions!$B$4)^(A28-Assumptions!$B$6) -> 721.33672 | I28: =I8/(1+Assumptions!$B$4)^(A28-Assumptions!$B$6) -> 1242.198 | J28: =J8/(1+Assumptions!$B$4)^(A28-Assumptions!$B$6) -> 1763.0593
A29: =A9 -> 2029 | B29: =B9/(1+Assumptions!$B$4)^(A29-Assumptions!$B$6) -> 1328.2041 | C29: =C9/(1+Assumptions!$B$4)^(A29-Assumptions!$B$6) -> 1210.8748 | D29: =D9/(1+Assumptions!$B$4)^(A29-Assumptions!$B$6) -> 2115.5935 | E29: =E9/(1+Assumptions!$B$4)^(A29-Assumptions!$B$6) -> 8716.2818 | F29: =F9/(1+Assumptions!$B$4)^(A29-Assumptions!$B$6) -> 2023.0134 | G29: =G9/(1+Assumptions!$B$4)^(A29-Assumptions!$B$6) -> 1187.9589 | H29: =H9/(1+Assumptions!$B$4)^(A29-Assumptions!$B$6) -> 707.64219 | I29: =I9/(1+Assumptions!$B$4)^(A29-Assumptions!$B$6) -> 1218.2079 | J29: =J9/(1+Assumptions!$B$4)^(A29-Assumptions!$B$6) -> 1729.6902
A30: =A10 -> 2030 | B30: =B10/(1+Assumptions!$B$4)^(A30-Assumptions!$B$6) -> 1314.8599 | C30: =C10/(1+Assumptions!$B$4)^(A30-Assumptions!$B$6) -> 1193.778 | D30: =D10/(1+Assumptions!$B$4)^(A30-Assumptions!$B$6) -> 2102.3408 | E30: =E10/(1+Assumptions!$B$4)^(A30-Assumptions!$B$6) -> 8608.4759 | F30: =F10/(1+Assumptions!$B$4)^(A30-Assumptions!$B$6) -> 2010.8567 | G30: =G10/(1+Assumptions!$B$4)^(A30-Assumptions!$B$6) -> 1171.3554 | H30: =H10/(1+Assumptions!$B$4)^(A30-Assumptions!$B$6) -> 697.79061 | I30: =I10/(1+Assumptions!$B$4)^(A30-Assumptions!$B$6) -> 1200.9532 | J30: =J10/(1+Assumptions!$B$4)^(A30-Assumptions!$B$6) -> 1705.0128
A31: =A11 -> 2031 | B31: =B11/(1+Assumptions!$B$4)^(A31-Assumptions!$B$6) -> 1304.9852 | C31: =C11/(1+Assumptions!$B$4)^(A31-Assumptions!$B$6) -> 1179.489 | D31: =D11/(1+Assumptions!$B$4)^(A31-Assumptions!$B$6) -> 2087.8008 | E31: =E11/(1+Assumptions!$B$4)^(A31-Assumptions!$B$6) -> 8526.7225 | F31: =F11/(1+Assumptions!$B$4)^(A31-Assumptions!$B$6) -> 2004.4292 | G31: =G11/(1+Assumptions!$B$4)^(A31-Assumptions!$B$6) -> 1147.0179 | H31: =H11/(1+Assumptions!$B$4)^(A31-Assumptions!$B$6) -> 689.79044 | I31: =I11/(1+Assumptions!$B$4)^(A31-Assumptions!$B$6) -> 1186.5098 | J31: =J11/(1+Assumptions!$B$4)^(A31-Assumptions!$B$6) -> 1684.9843
A32: =A12 -> 2032 | B32: =B12/(1+Assumptions!$B$4)^(A32-Assumptions!$B$6) -> 1294.9264 | C32: =C12/(1+Assumptions!$B$4)^(A32-Assumptions!$B$6) -> 1165.262 | D32: =D12/(1+Assumptions!$B$4)^(A32-Assumptions!$B$6) -> 2075.4887 | E32: =E12/(1+Assumptions!$B$4)^(A32-Assumptions!$B$6) -> 8441.9238 | F32: =F12/(1+Assumptions!$B$4)^(A32-Assumptions!$B$6) -> 1996.4879 | G32: =G12/(1+Assumptions!$B$4)^(A32-Assumptions!$B$6) -> 1125.7616 | H32: =H12/(1+Assumptions!$B$4)^(A32-Assumptions!$B$6) -> 677.51784 | I32: =I12/(1+Assumptions!$B$4)^(A32-Assumptions!$B$6) -> 1166.9794 | J32: =J12/(1+Assumptions!$B$4)^(A32-Assumptions!$B$6) -> 1656.4409
A33: =A13 -> 2033 | B33: =B13/(1+Assumptions!$B$4)^(A33-Assumptions!$B$6) -> 1284.6958 | C33: =C13/(1+Assumptions!$B$4)^(A33-Assumptions!$B$6) -> 1150.2607 | D33: =D13/(1+Assumptions!$B$4)^(A33-Assumptions!$B$6) -> 2063.5795 | E33: =E13/(1+Assumptions!$B$4)^(A33-Assumptions!$B$6) -> 8350.1029 | F33: =F13/(1+Assumptions!$B$4)^(A33-Assumptions!$B$6) -> 1987.1195 | G33: =G13/(1+Assumptions!$B$4)^(A33-Assumptions!$B$6) -> 1103.2084 | H33: =H13/(1+Assumptions!$B$4)^(A33-Assumptions!$B$6) -> 667.97462 | I33: =I13/(1+Assumptions!$B$4)^(A33-Assumptions!$B$6) -> 1149.4205 | J33: =J13/(1+Assumptions!$B$4)^(A33-Assumptions!$B$6) -> 1631.7066
A34: =A14 -> 2034 | B34: =B14/(1+Assumptions!$B$4)^(A34-Assumptions!$B$6) -> 1266.0844 | C34: =C14/(1+Assumptions!$B$4)^(A34-Assumptions!$B$6) -> 1121.389 | D34: =D14/(1+Assumptions!$B$4)^(A34-Assumptions!$B$6) -> 2050.399 | E34: =E14/(1+Assumptions!$B$4)^(A34-Assumptions!$B$6) -> 8248.4577 | F34: =F14/(1+Assumptions!$B$4)^(A34-Assumptions!$B$6) -> 1975.5849 | G34: =G14/(1+Assumptions!$B$4)^(A34-Assumptions!$B$6) -> 1078.6381 | H34: =H14/(1+Assumptions!$B$4)^(A34-Assumptions!$B$6) -> 656.06192 | I34: =I14/(1+Assumptions!$B$4)^(A34-Assumptions!$B$6) -> 1129.6104 | J34: =J14/(1+Assumptions!$B$4)^(A34-Assumptions!$B$6) -> 1603.1588
A35: =A15 -> 2035 | B35: =B15/(1+Assumptions!$B$4)^(A35-Assumptions!$B$6) -> 1254.1144 | C35: =C15/(1+Assumptions!$B$4)^(A35-Assumptions!$B$6) -> 1109.3161 | D35: =D15/(1+Assumptions!$B$4)^(A35-Assumptions!$B$6) -> 2036.8298 | E35: =E15/(1+Assumptions!$B$4)^(A35-Assumptions!$B$6) -> 8133.6439 | F35: =F15/(1+Assumptions!$B$4)^(A35-Assumptions!$B$6) -> 1960.4085 | G35: =G15/(1+Assumptions!$B$4)^(A35-Assumptions!$B$6) -> 1052.2012 | H35: =H15/(1+Assumptions!$B$4)^(A35-Assumptions!$B$6) -> 645.15699 | I35: =I15/(1+Assumptions!$B$4)^(A35-Assumptions!$B$6) -> 1110.9249 | J35: =J15/(1+Assumptions!$B$4)^(A35-Assumptions!$B$6) -> 1576.6929
A36: =A16 -> 2036 | B36: =B16/(1+Assumptions!$B$4)^(A36-Assumptions!$B$6) -> 1244.4344 | C36: =C16/(1+Assumptions!$B$4)^(A36-Assumptions!$B$6) -> 1098.0304 | D36: =D16/(1+Assumptions!$B$4)^(A36-Assumptions!$B$6) -> 2021.3204 | E36: =E16/(1+Assumptions!$B$4)^(A36-Assumptions!$B$6) -> 8029.3963 | F36: =F16/(1+Assumptions!$B$4)^(A36-Assumptions!$B$6) -> 1948.1184 | G36: =G16/(1+Assumptions!$B$4)^(A36-Assumptions!$B$6) -> 1029.5511 | H36: =H16/(1+Assumptions!$B$4)^(A36-Assumptions!$B$6) -> 634.41755 | I36: =I16/(1+Assumptions!$B$4)^(A36-Assumptions!$B$6) -> 1091.7334 | J36: =J16/(1+Assumptions!$B$4)^(A36-Assumptions!$B$6) -> 1549.8364
A37: =A17 -> 2037 | B37: =B17/(1+Assumptions!$B$4)^(A37-Assumptions!$B$6) -> 1236.9006 | C37: =C17/(1+Assumptions!$B$4)^(A37-Assumptions!$B$6) -> 1089.7972 | D37: =D17/(1+Assumptions!$B$4)^(A37-Assumptions!$B$6) -> 2007.0753 | E37: =E17/(1+Assumptions!$B$4)^(A37-Assumptions!$B$6) -> 7941.2714 | F37: =F17/(1+Assumptions!$B$4)^(A37-Assumptions!$B$6) -> 1939.2999 | G37: =G17/(1+Assumptions!$B$4)^(A37-Assumptions!$B$6) -> 1014.3201 | H37: =H17/(1+Assumptions!$B$4)^(A37-Assumptions!$B$6) -> 623.84151 | I37: =I17/(1+Assumptions!$B$4)^(A37-Assumptions!$B$6) -> 1073.6235 | J37: =J17/(1+Assumptions!$B$4)^(A37-Assumptions!$B$6) -> 1524.1757
A38: =A18 -> 2038 | B38: =B18/(1+Assumptions!$B$4)^(A38-Assumptions!$B$6) -> 1230.6216 | C38: =C18/(1+Assumptions!$B$4)^(A38-Assumptions!$B$6) -> 1082.9169 | D38: =D18/(1+Assumptions!$B$4)^(A38-Assumptions!$B$6) -> 1993.2604 | E38: =E18/(1+Assumptions!$B$4)^(A38-Assumptions!$B$6) -> 7856.2341 | F38: =F18/(1+Assumptions!$B$4)^(A38-Assumptions!$B$6) -> 1931.4655 | G38: =G18/(1+Assumptions!$B$4)^(A38-Assumptions!$B$6) -> 1000.775 | H38: =H18/(1+Assumptions!$B$4)^(A38-Assumptions!$B$6) -> 613.42682 | I38: =I18/(1+Assumptions!$B$4)^(A38-Assumptions!$B$6) -> 1056.541 | J38: =J18/(1+Assumptions!$B$4)^(A38-Assumptions!$B$6) -> 1499.6552
... A41: =A21 -> 2041 | B41: =B21/(1+Assumptions!$B$4)^(A41-Assumptions!$B$6) -> 1210.031 | C41: =C21/(1+Assumptions!$B$4)^(A41-Assumptions!$B$6) -> 1060.3655 | D41: =D21/(1+Assumptions!$B$4)^(A41-Assumptions!$B$6) -> 1952.7104 | E41: =E21/(1+Assumptions!$B$4)^(A41-Assumptions!$B$6) -> 7596.2271 | F41: =F21/(1+Assumptions!$B$4)^(A41-Assumptions!$B$6) -> 1906.1165 | G41: =G21/(1+Assumptions!$B$4)^(A41-Assumptions!$B$6) -> 971.41342 | H41: =H21/(1+Assumptions!$B$4)^(A41-Assumptions!$B$6) -> 585.24835 | I41: =I21/(1+Assumptions!$B$4)^(A41-Assumptions!$B$6) -> 1008.1238 | J41: =J21/(1+Assumptions!$B$4)^(A41-Assumptions!$B$6) -> 1430.9993
A43: Notes
A44: ERCOT's source table is nominal $/kW; the 2025$ table uses ERCOT's 2.2% annual inflation assumption.
A45: These are the preferred ERCOT-specific base-case new-build CAPEX assumptions in this workbook.
A46: FOM/VOM are not supplied in this LTSA capital-cost table; see EIA and ATB sheets.

Sheet EIA_AEO2026_TRE
A1: EIA AEO2026 — New-Build Cost & Performance Assumptions (TRE / Texas)
A2: Source: | B2: https://www.eia.gov/outlooks/aeo/assumptions/pdf/EMM_Assumptions.pdf
A4: Technology | B4: First available year | C4: Size (MW) | D4: Lead time (yr) | E4: Base overnight cost (2025$/kW) | F4: Total overnight cost (2025$/kW) | G4: TRE regional overnight cost (2025$/kW) | H4: FOM (2025$/kW-yr) | I4: VOM (2025$/MWh) | J4: Heat rate / EIA convention (Btu/kWh) | K4: Notes | L4: Source URL
A5: CC single-shaft | B5: 2028 | C5: 627 | D5: 3 | E5: 1086 | F5: 1086 | G5: 980 | H5: 16.23 | I5: 3.49 | J5: 6226 | K5: TRE = Texas Reliability Entity | L5: https://www.eia.gov/outlooks/aeo/assumptions/pdf/EMM_Assumptions.pdf
A6: CC multi-shaft | B6: 2028 | C6: 1227 | D6: 3 | E6: 1032 | F6: 1032 | G6: 930 | H6: 12.69 | I6: 3.57 | J6: 6226 | K6: Preferred EIA comparator for ERCOT CC | L6: https://www.eia.gov/outlooks/aeo/assumptions/pdf/EMM_Assumptions.pdf
A7: CC with 95% CCS | B7: 2029 | C7: 543 | D7: 4 | E7: 2567 | F7: 2824 | G7: 2504 | H7: 25.93 | I7: 5.29 | J7: 7239 | L7: https://www.eia.gov/outlooks/aeo/assumptions/pdf/EMM_Assumptions.pdf
A8: CT aeroderivative | B8: 2027 | C8: 211 | D8: 2 | E8: 2275 | F8: 2275 | G8: 2058 | H8: 9.99 | I8: 5.97 | J8: 9447 | L8: https://www.eia.gov/outlooks/aeo/assumptions/pdf/EMM_Assumptions.pdf
A9: CT industrial frame | B9: 2027 | C9: 419 | D9: 2 | E9: 1158 | F9: 1158 | G9: 1033 | H9: 7.18 | I9: 4.17 | J9: 9142 | K9: Preferred EIA comparator for ERCOT CT | L9: https://www.eia.gov/outlooks/aeo/assumptions/pdf/EMM_Assumptions.pdf
A10: Nuclear - large LWR | B10: 2031 | C10: 2156 | D10: 6 | E10: 7862 | F10: 8255 | G10: 7866 | H10: 163.4 | I10: 2.62 | J10: 10445 | L10: https://www.eia.gov/outlooks/aeo/assumptions/pdf/EMM_Assumptions.pdf
A11: Nuclear - SMR | B11: 2031 | C11: 480 | D11: 6 | E11: 8937 | F11: 9831 | G11: 9366 | H11: 127.62 | I11: 3.32 | J11: 10445 | L11: https://www.eia.gov/outlooks/aeo/assumptions/pdf/EMM_Assumptions.pdf
A12: Battery storage - 4h Li-ion | B12: 2026 | C12: 150 | D12: 1 | E12: 1521 | F12: 1521 | G12: 1500 | H12: 41.84 | I12: 0 | K12: EIA defines battery storage as four-hour Li-ion | L12: https://www.eia.gov/outlooks/aeo/assumptions/pdf/EMM_Assumptions.pdf
A13: Wind - onshore | B13: 2028 | C13: 200 | D13: 3 | E13: 1712 | F13: 1712 | G13: 1562 | H13: 34.57 | I13: 0 | J13: 3412 | K13: 3,412 is EIA primary-energy heat-content convention, not a thermal efficiency | L13: https://www.eia.gov/outlooks/aeo/assumptions/pdf/EMM_Assumptions.pdf
A14: Solar PV - tracking | B14: 2027 | C14: 150 | D14: 2 | E14: 1484 | F14: 1484 | G14: 1342 | H14: 23.6 | I14: 0 | J14: 3412 | K14: Costs/capacity expressed on an AC basis | L14: https://www.eia.gov/outlooks/aeo/assumptions/pdf/EMM_Assumptions.pdf
A15: Solar PV + storage | B15: 2027 | C15: 150 | D15: 2 | E15: 1903 | F15: 1903 | G15: 1840 | H15: 40 | I15: 0 | J15: 3412 | K15: 150 MW PV + 50 MW four-hour battery | L15: https://www.eia.gov/outlooks/aeo/assumptions/pdf/EMM_Assumptions.pdf
A18: Interpretation
A19: TRE is EIA region 1, Texas Reliability Entity. Use the TRE cost as a regional cross-check, not as an explicit EIA 2030/2035 point.
A20: AEO2026 updated CC/CT inputs for recent turbine, materials, and labor tightness and applies regional/locality adjustments.
A21: EIA explicitly represents battery storage as a four-hour lithium-ion battery.

Sheet NLR_ATB_2024b
A1: NLR/NREL 2024b ATB v4 — 2030 / 2035 Cost Scenarios
A2: Source workbook: | B2: https://data.openei.org/files/6006/2024_v4_Workbook_7-22-2026.xlsx
A4: Technology | B4: ATB detail | C4: Scenario | D4: CRP years | E4: CAPEX 2030 (2022$/kW) | F4: CAPEX 2035 (2022$/kW) | G4: FOM 2030 (2022$/kW-yr) | H4: FOM 2035 (2022$/kW-yr) | I4: VOM 2030 (2022$/MWh) | J4: VOM 2035 (2022$/MWh) | K4: CAPEX 2030 (2025$/kW) | L4: CAPEX 2035 (2025$/kW) | M4: FOM 2030 (2025$/kW-yr) | N4: FOM 2035 (2025$/kW-yr) | O4: VOM 2030 (2025$/MWh) | P4: VOM 2035 (2025$/MWh) | Q4: Source URL
A5: CC F-frame | B5: NG 2-on-1 Combined Cycle (F-Frame) | C5: Advanced | D5: 30 | E5: 1381.1314 | F5: 1307.2497 | G5: 30.7 | H5: 28.3 | I5: 2 | J5: 1.89 | K5: =E5*Assumptions!$C$9 -> 1519.3508 | L5: =F5*Assumptions!$C$9 -> 1438.0752 | M5: =G5*Assumptions!$C$9 -> 33.77236 | N5: =H5*Assumptions!$C$9 -> 31.132176 | O5: =I5*Assumptions!$C$9 -> 2.2001538 | P5: =J5*Assumptions!$C$9 -> 2.0791453 | Q5: https://data.openei.org/files/6006/2024_v4_Workbook_7-22-2026.xlsx
A6: CC F-frame | B6: NG 2-on-1 Combined Cycle (F-Frame) | C6: Moderate | D6: 30 | E6: 1403.3071 | F6: 1343.3548 | G6: 31.8 | H6: 30.1 | I6: 2.04 | J6: 1.96 | K6: =E6*Assumptions!$C$9 -> 1543.7457 | L6: =F6*Assumptions!$C$9 -> 1477.7936 | M6: =G6*Assumptions!$C$9 -> 34.982445 | N6: =H6*Assumptions!$C$9 -> 33.112314 | O6: =I6*Assumptions!$C$9 -> 2.2441568 | P6: =J6*Assumptions!$C$9 -> 2.1561507 | Q6: https://data.openei.org/files/6006/2024_v4_Workbook_7-22-2026.xlsx
A7: CC F-frame | B7: NG 2-on-1 Combined Cycle (F-Frame) | C7: Conservative | D7: 30 | E7: 1425.4828 | F7: 1379.3485 | G7: 32.8 | H7: 31.8 | I7: 2.08 | J7: 2.03 | K7: =E7*Assumptions!$C$9 -> 1568.1406 | L7: =F7*Assumptions!$C$9 -> 1517.3894 | M7: =G7*Assumptions!$C$9 -> 36.082522 | N7: =H7*Assumptions!$C$9 -> 34.982445 | O7: =I7*Assumptions!$C$9 -> 2.2881599 | P7: =J7*Assumptions!$C$9 -> 2.2331561 | Q7: https://data.openei.org/files/6006/2024_v4_Workbook_7-22-2026.xlsx
A8: CT F-frame | B8: NG Combustion Turbine (F-Frame) | C8: Advanced | D8: 30 | E8: 1270.476 | F8: 1221.4444 | G8: 25 | H8: 24.2 | I8: 6.94 | J8: 6.94 | K8: =E8*Assumptions!$C$9 -> 1397.6213 | L8: =F8*Assumptions!$C$9 -> 1343.6827 | M8: =G8*Assumptions!$C$9 -> 27.501922 | N8: =H8*Assumptions!$C$9 -> 26.621861 | O8: =I8*Assumptions!$C$9 -> 7.6345336 | P8: =J8*Assumptions!$C$9 -> 7.6345336 | Q8: https://data.openei.org/files/6006/2024_v4_Workbook_7-22-2026.xlsx
A9: CT F-frame | B9: NG Combustion Turbine (F-Frame) | C9: Moderate | D9: 30 | E9: 1270.476 | F9: 1221.4444 | G9: 25 | H9: 24.2 | I9: 6.94 | J9: 6.94 | K9: =E9*Assumptions!$C$9 -> 1397.6213 | L9: =F9*Assumptions!$C$9 -> 1343.6827 | M9: =G9*Assumptions!$C$9 -> 27.501922 | N9: =H9*Assumptions!$C$9 -> 26.621861 | O9: =I9*Assumptions!$C$9 -> 7.6345336 | P9: =J9*Assumptions!$C$9 -> 7.6345336 | Q9: https://data.openei.org/files/6006/2024_v4_Workbook_7-22-2026.xlsx
A10: CT F-frame | B10: NG Combustion Turbine (F-Frame) | C10: Conservative | D10: 30 | E10: 1270.476 | F10: 1221.4444 | G10: 25 | H10: 24.2 | I10: 6.94 | J10: 6.94 | K10: =E10*Assumptions!$C$9 -> 1397.6213 | L10: =F10*Assumptions!$C$9 -> 1343.6827 | M10: =G10*Assumptions!$C$9 -> 27.501922 | N10: =H10*Assumptions!$C$9 -> 26.621861 | O10: =I10*Assumptions!$C$9 -> 7.6345336 | P10: =J10*Assumptions!$C$9 -> 7.6345336 | Q10: https://data.openei.org/files/6006/2024_v4_Workbook_7-22-2026.xlsx
A11: SMR | B11: Nuclear - Small | C11: Advanced | D11: 30 | E11: 6416.7403 | F11: 3838.5857 | G11: 118 | H11: 118 | I11: 2.2 | J11: 2.2 | K11: =E11*Assumptions!$C$9 -> 7058.9076 | L11: =F11*Assumptions!$C$9 -> 4222.7394 | M11: =G11*Assumptions!$C$9 -> 129.80907 | N11: =H11*Assumptions!$C$9 -> 129.80907 | O11: =I11*Assumptions!$C$9 -> 2.4201691 | P11: =J11*Assumptions!$C$9 -> 2.4201691 | Q11: https://data.openei.org/files/6006/2024_v4_Workbook_7-22-2026.xlsx
A12: SMR | B12: Nuclear - Small | C12: Moderate | D12: 30 | E12: 9650.0007 | F12: 7862.9635 | G12: 136 | H12: 136 | I12: 2.6 | J12: 2.6 | K12: =E12*Assumptions!$C$9 -> 10615.743 | L12: =F12*Assumptions!$C$9 -> 8649.8644 | M12: =G12*Assumptions!$C$9 -> 149.61046 | N12: =H12*Assumptions!$C$9 -> 149.61046 | O12: =I12*Assumptions!$C$9 -> 2.8601999 | P12: =J12*Assumptions!$C$9 -> 2.8601999 | Q12: https://data.openei.org/files/6006/2024_v4_Workbook_7-22-2026.xlsx
A13: SMR | B13: Nuclear - Small | C13: Conservative | D13: 30 | E13: 12681.127 | F13: 12053.348 | G13: 216 | H13: 216 | I13: 2.8 | J13: 2.8 | K13: =E13*Assumptions!$C$9 -> 13950.214 | L13: =F13*Assumptions!$C$9 -> 13259.61 | M13: =G13*Assumptions!$C$9 -> 237.61661 | N13: =H13*Assumptions!$C$9 -> 237.61661 | O13: =I13*Assumptions!$C$9 -> 3.0802153 | P13: =J13*Assumptions!$C$9 -> 3.0802153 | Q13: https://data.openei.org/files/6006/2024_v4_Workbook_7-22-2026.xlsx
A14: Wind class 1 | B14: Land-Based Wind - Class 1 - Technology 1 | C14: Advanced | D14: 30 | E14: 1341.6723 | F14: 1258.7993 | G14: 26.314454 | H14: 23.834381 | I14: 0 | J14: 0 | K14: =E14*Assumptions!$C$9 -> 1475.9427 | L14: =F14*Assumptions!$C$9 -> 1384.776 | M14: =G14*Assumptions!$C$9 -> 28.947922 | N14: =H14*Assumptions!$C$9 -> 26.219652 | O14: =I14*Assumptions!$C$9 -> 0 | P14: =J14*Assumptions!$C$9 -> 0 | Q14: https://data.openei.org/files/6006/2024_v4_Workbook_7-22-2026.xlsx
A15: Wind class 1 | B15: Land-Based Wind - Class 1 - Technology 1 | C15: Moderate | D15: 30 | E15: 1407.9532 | F15: 1334.692 | G15: 29.263773 | H15: 28.261218 | I15: 0 | J15: 0 | K15: =E15*Assumptions!$C$9 -> 1548.8568 | L15: =F15*Assumptions!$C$9 -> 1468.2638 | M15: =G15*Assumptions!$C$9 -> 32.1924 | N15: =H15*Assumptions!$C$9 -> 31.089513 | O15: =I15*Assumptions!$C$9 -> 0 | P15: =J15*Assumptions!$C$9 -> 0 | Q15: https://data.openei.org/files/6006/2024_v4_Workbook_7-22-2026.xlsx
A16: Wind class 1 | B16: Land-Based Wind - Class 1 - Technology 1 | C16: Conservative | D16: 30 | E16: 1577.3918 | F16: 1522.1515 | G16: 30.910899 | H16: 30.290881 | I16: 0 | J16: 0 | K16: =E16*Assumptions!$C$9 -> 1735.2522 | L16: =F16*Assumptions!$C$9 -> 1674.4837 | M16: =G16*Assumptions!$C$9 -> 34.004365 | N16: =H16*Assumptions!$C$9 -> 33.322298 | O16: =I16*Assumptions!$C$9 -> 0 | P16: =J16*Assumptions!$C$9 -> 0 | Q16: https://data.openei.org/files/6006/2024_v4_Workbook_7-22-2026.xlsx
... A22: Solar PV | B22: Utility PV - Class 1 | C22: Conservative | D22: 30 | E22: 1364.9377 | F22: 1189.2471 | G22: 19.724805 | H22: 17.961888 | I22: 0 | J22: 0 | K22: =E22*Assumptions!$C$9 -> 1501.5365 | L22: =F22*Assumptions!$C$9 -> 1308.2632 | M22: =G22*Assumptions!$C$9 -> 21.698802 | N22: =H22*Assumptions!$C$9 -> 19.759458 | O22: =I22*Assumptions!$C$9 -> 0 | P22: =J22*Assumptions!$C$9 -> 0 | Q22: https://data.openei.org/files/6006/2024_v4_Workbook_7-22-2026.xlsx
A23: BESS 2h | B23: Utility-Scale Battery Storage - 2Hr | C23: Advanced | D23: * | E23: 706.0799 | F23: 652.792 | G23: 14.529716 | H23: 13.244482 | I23: 0 | J23: 0 | K23: =E23*Assumptions!$C$9 -> 776.74218 | L23: =F23*Assumptions!$C$9 -> 718.12139 | M23: =G23*Assumptions!$C$9 -> 15.983805 | N23: =H23*Assumptions!$C$9 -> 14.569948 | O23: =I23*Assumptions!$C$9 -> 0 | P23: =J23*Assumptions!$C$9 -> 0 | Q23: https://data.openei.org/files/6006/2024_v4_Workbook_7-22-2026.xlsx
A24: BESS 2h | B24: Utility-Scale Battery Storage - 2Hr | C24: Moderate | D24: * | E24: 941.9756 | F24: 884.34444 | G24: 20.219209 | H24: 18.829221 | I24: 0 | J24: 0 | K24: =E24*Assumptions!$C$9 -> 1036.2456 | L24: =F24*Assumptions!$C$9 -> 972.84687 | M24: =G24*Assumptions!$C$9 -> 22.242684 | N24: =H24*Assumptions!$C$9 -> 20.713591 | O24: =I24*Assumptions!$C$9 -> 0 | P24: =J24*Assumptions!$C$9 -> 0 | Q24: https://data.openei.org/files/6006/2024_v4_Workbook_7-22-2026.xlsx
A25: BESS 2h | B25: Utility-Scale Battery Storage - 2Hr | C25: Conservative | D25: * | E25: 1114.4629 | F25: 1079.859 | G25: 24.379376 | H25: 23.544775 | I25: 0 | J25: 0 | K25: =E25*Assumptions!$C$9 -> 1225.9949 | L25: =F25*Assumptions!$C$9 -> 1187.9279 | M25: =G25*Assumptions!$C$9 -> 26.819188 | N25: =H25*Assumptions!$C$9 -> 25.901062 | O25: =I25*Assumptions!$C$9 -> 0 | P25: =J25*Assumptions!$C$9 -> 0 | Q25: https://data.openei.org/files/6006/2024_v4_Workbook_7-22-2026.xlsx
A26: BESS 4h | B26: Utility-Scale Battery Storage - 4Hr | C26: Advanced | D26: * | E26: 1117.5994 | F26: 1028.7117 | G26: 24.455023 | H26: 22.311171 | I26: 0 | J26: 0 | K26: =E26*Assumptions!$C$9 -> 1229.4452 | L26: =F26*Assumptions!$C$9 -> 1131.662 | M26: =G26*Assumptions!$C$9 -> 26.902405 | N26: =H26*Assumptions!$C$9 -> 24.544003 | O26: =I26*Assumptions!$C$9 -> 0 | P26: =J26*Assumptions!$C$9 -> 0 | Q26: https://data.openei.org/files/6006/2024_v4_Workbook_7-22-2026.xlsx
A27: BESS 4h | B27: Utility-Scale Battery Storage - 4Hr | C27: Moderate | D27: * | E27: 1451.3156 | F27: 1347.3964 | G27: 32.503818 | H27: 29.997424 | I27: 0 | J27: 0 | K27: =E27*Assumptions!$C$9 -> 1596.5588 | L27: =F27*Assumptions!$C$9 -> 1482.2396 | M27: =G27*Assumptions!$C$9 -> 35.756699 | N27: =H27*Assumptions!$C$9 -> 32.999473 | O27: =I27*Assumptions!$C$9 -> 0 | P27: =J27*Assumptions!$C$9 -> 0 | Q27: https://data.openei.org/files/6006/2024_v4_Workbook_7-22-2026.xlsx
A28: BESS 4h | B28: Utility-Scale Battery Storage - 4Hr | C28: Conservative | D28: * | E28: 1774.9148 | F28: 1717.701 | G28: 40.308604 | H28: 38.928683 | I28: 0 | J28: 0 | K28: =E28*Assumptions!$C$9 -> 1952.5427 | L28: =F28*Assumptions!$C$9 -> 1889.6032 | M28: =G28*Assumptions!$C$9 -> 44.342563 | N28: =H28*Assumptions!$C$9 -> 42.824544 | O28: =I28*Assumptions!$C$9 -> 0 | P28: =J28*Assumptions!$C$9 -> 0 | Q28: https://data.openei.org/files/6006/2024_v4_Workbook_7-22-2026.xlsx
A29: BESS 6h | B29: Utility-Scale Battery Storage - 6Hr | C29: Advanced | D29: * | E29: 1529.1188 | F29: 1404.6315 | G29: 34.380329 | H29: 31.377859 | I29: 0 | J29: 0 | K29: =E29*Assumptions!$C$9 -> 1682.1483 | L29: =F29*Assumptions!$C$9 -> 1545.2026 | M29: =G29*Assumptions!$C$9 -> 37.821005 | N29: =H29*Assumptions!$C$9 -> 34.518057 | O29: =I29*Assumptions!$C$9 -> 0 | P29: =J29*Assumptions!$C$9 -> 0 | Q29: https://data.openei.org/files/6006/2024_v4_Workbook_7-22-2026.xlsx
A30: BESS 6h | B30: Utility-Scale Battery Storage - 6Hr | C30: Moderate | D30: * | E30: 1960.6556 | F30: 1810.4484 | G30: 44.788428 | H30: 41.165627 | I30: 0 | J30: 0 | K30: =E30*Assumptions!$C$9 -> 2156.8719 | L30: =F30*Assumptions!$C$9 -> 1991.6324 | M30: =G30*Assumptions!$C$9 -> 49.270714 | N30: =H30*Assumptions!$C$9 -> 45.285354 | O30: =I30*Assumptions!$C$9 -> 0 | P30: =J30*Assumptions!$C$9 -> 0 | Q30: https://data.openei.org/files/6006/2024_v4_Workbook_7-22-2026.xlsx
A31: BESS 6h | B31: Utility-Scale Battery Storage - 6Hr | C31: Conservative | D31: * | E31: 2435.3667 | F31: 2355.543 | G31: 56.237832 | H31: 54.312591 | I31: 0 | J31: 0 | K31: =E31*Assumptions!$C$9 -> 2679.0906 | L31: =F31*Assumptions!$C$9 -> 2591.2784 | M31: =G31*Assumptions!$C$9 -> 61.865939 | N31: =H31*Assumptions!$C$9 -> 59.748026 | O31: =I31*Assumptions!$C$9 -> 0 | P31: =J31*Assumptions!$C$9 -> 0 | Q31: https://data.openei.org/files/6006/2024_v4_Workbook_7-22-2026.xlsx
A34: Notes
A35: ATB 2024b monetary values are in 2022 dollars.
A36: The December 2025 2024b reference refresh did not change the underlying ATB data.
A37: Wind Classes 1 and 7 are both retained because the resource/site class choice can affect CAPEX and is relevant for ERCOT.

Sheet NLR_BESS_2025
A1: NLR 2025 Utility-Scale Battery Cost Projection — 4-hour Li-ion
A2: Source: | B2: https://www.nlr.gov/docs/fy25osti/93281.pdf
A4: Year | B4: Low (2024$/kWh) | C4: Mid (2024$/kWh) | D4: High (2024$/kWh) | E4: Low 4h (2024$/kW) | F4: Mid 4h (2024$/kW) | G4: High 4h (2024$/kW) | H4: Low 4h (2025$/kW) | I4: Mid 4h (2025$/kW) | J4: High 4h (2025$/kW) | K4: Source URL
A5: 2024 | B5: 334 | C5: 334 | D5: 334 | E5: =B5*4 -> 1336 | F5: =C5*4 -> 1336 | G5: =D5*4 -> 1336 | H5: =E5*Assumptions!$C$11 -> 1371.1537 | I5: =F5*Assumptions!$C$11 -> 1371.1537 | J5: =G5*Assumptions!$C$11 -> 1371.1537 | K5: https://www.nlr.gov/docs/fy25osti/93281.pdf
A6: 2025 | B6: 295 | C6: 321 | D6: 350 | E6: =B6*4 -> 1180 | F6: =C6*4 -> 1284 | G6: =D6*4 -> 1400 | H6: =E6*Assumptions!$C$11 -> 1211.049 | I6: =F6*Assumptions!$C$11 -> 1317.7855 | J6: =G6*Assumptions!$C$11 -> 1436.8378 | K6: https://www.nlr.gov/docs/fy25osti/93281.pdf
A7: 2026 | B7: 255 | C7: 308 | D7: 366 | E7: =B7*4 -> 1020 | F7: =C7*4 -> 1232 | G7: =D7*4 -> 1464 | H7: =E7*Assumptions!$C$11 -> 1046.8389 | I7: =F7*Assumptions!$C$11 -> 1264.4172 | J7: =G7*Assumptions!$C$11 -> 1502.5218 | K7: https://www.nlr.gov/docs/fy25osti/93281.pdf
A8: 2027 | B8: 243 | C8: 301 | D8: 363 | E8: =B8*4 -> 972 | F8: =C8*4 -> 1204 | G8: =D8*4 -> 1452 | H8: =E8*Assumptions!$C$11 -> 997.57593 | I8: =F8*Assumptions!$C$11 -> 1235.6805 | J8: =G8*Assumptions!$C$11 -> 1490.206 | K8: https://www.nlr.gov/docs/fy25osti/93281.pdf
A9: 2028 | B9: 231 | C9: 293 | D9: 360 | E9: =B9*4 -> 924 | F9: =C9*4 -> 1172 | G9: =D9*4 -> 1440 | H9: =E9*Assumptions!$C$11 -> 948.31292 | I9: =F9*Assumptions!$C$11 -> 1202.8385 | J9: =G9*Assumptions!$C$11 -> 1477.8903 | K9: https://www.nlr.gov/docs/fy25osti/93281.pdf
A10: 2029 | B10: 219 | C10: 286 | D10: 357 | E10: =B10*4 -> 876 | F10: =C10*4 -> 1144 | G10: =D10*4 -> 1428 | H10: =E10*Assumptions!$C$11 -> 899.04991 | I10: =F10*Assumptions!$C$11 -> 1174.1017 | J10: =G10*Assumptions!$C$11 -> 1465.5745 | K10: https://www.nlr.gov/docs/fy25osti/93281.pdf
A11: 2030 | B11: 207 | C11: 279 | D11: 354 | E11: =B11*4 -> 828 | F11: =C11*4 -> 1116 | G11: =D11*4 -> 1416 | H11: =E11*Assumptions!$C$11 -> 849.7869 | I11: =F11*Assumptions!$C$11 -> 1145.365 | J11: =G11*Assumptions!$C$11 -> 1453.2588 | K11: https://www.nlr.gov/docs/fy25osti/93281.pdf
A12: 2031 | B12: 195 | C12: 272 | D12: 351 | E12: =B12*4 -> 780 | F12: =C12*4 -> 1088 | G12: =D12*4 -> 1404 | H12: =E12*Assumptions!$C$11 -> 800.52389 | I12: =F12*Assumptions!$C$11 -> 1116.6282 | J12: =G12*Assumptions!$C$11 -> 1440.943 | K12: https://www.nlr.gov/docs/fy25osti/93281.pdf
A13: 2032 | B13: 183 | C13: 265 | D13: 348 | E13: =B13*4 -> 732 | F13: =C13*4 -> 1060 | G13: =D13*4 -> 1392 | H13: =E13*Assumptions!$C$11 -> 751.26089 | I13: =F13*Assumptions!$C$11 -> 1087.8914 | J13: =G13*Assumptions!$C$11 -> 1428.6273 | K13: https://www.nlr.gov/docs/fy25osti/93281.pdf
A14: 2033 | B14: 171 | C14: 257 | D14: 345 | E14: =B14*4 -> 684 | F14: =C14*4 -> 1028 | G14: =D14*4 -> 1380 | H14: =E14*Assumptions!$C$11 -> 701.99788 | I14: =F14*Assumptions!$C$11 -> 1055.0494 | J14: =G14*Assumptions!$C$11 -> 1416.3115 | K14: https://www.nlr.gov/docs/fy25osti/93281.pdf
A15: 2034 | B15: 159 | C15: 250 | D15: 342 | E15: =B15*4 -> 636 | F15: =C15*4 -> 1000 | G15: =D15*4 -> 1368 | H15: =E15*Assumptions!$C$11 -> 652.73487 | I15: =F15*Assumptions!$C$11 -> 1026.3127 | J15: =G15*Assumptions!$C$11 -> 1403.9958 | K15: https://www.nlr.gov/docs/fy25osti/93281.pdf
A16: 2035 | B16: 147 | C16: 243 | D16: 339 | E16: =B16*4 -> 588 | F16: =C16*4 -> 972 | G16: =D16*4 -> 1356 | H16: =E16*Assumptions!$C$11 -> 603.47186 | I16: =F16*Assumptions!$C$11 -> 997.57593 | J16: =G16*Assumptions!$C$11 -> 1391.68 | K16: https://www.nlr.gov/docs/fy25osti/93281.pdf
... A21: 2040 | B21: 134 | C21: 221 | D21: 329 | E21: =B21*4 -> 536 | F21: =C21*4 -> 884 | G21: =D21*4 -> 1316 | H21: =E21*Assumptions!$C$11 -> 550.1036 | I21: =F21*Assumptions!$C$11 -> 907.26041 | J21: =G21*Assumptions!$C$11 -> 1350.6275 | K21: https://www.nlr.gov/docs/fy25osti/93281.pdf
A24: Notes
A25: The report states that $/kWh can be converted to $/kW by multiplying by storage duration; this sheet uses four hours.
A26: Use this newer series as a battery-specific sensitivity to the older ATB trajectory.

Sheet LBNL_Actuals
A1: Berkeley Lab — Empirical Installed-Cost Benchmarks (Calibration Only)
A4: Technology | B4: Region | C4: Project/COD year(s) | D4: Raw installed cost | E4: Raw unit / dollar year | F4: 2025$/kW equivalent | G4: Use in ERCOT CEM | H4: Notes | I4: Source URL
A5: Land-based wind | B5: ERCOT | C5: 2022–2023 | D5: 1370 | E5: 2023$/kW | F5: =D5*Assumptions!$C$10 -> 1447.5189 | G5: Strong empirical ERCOT calibration | H5: Capacity-weighted regional mean; historical, not a forward forecast | I5: https://emp.lbl.gov/sites/default/files/2024-08/Land-Based%20Wind%20Market%20Report_2024%20Edition.pdf
A6: Utility-scale solar PV | B6: U.S. | C6: 2024 | D6: 1610 | E6: 2024$/kW-AC | F6: =D6*Assumptions!$C$11 -> 1652.3634 | G6: National empirical calibration | H6: Capacity-weighted mean; preliminary 2024 sample; not ERCOT-specific | I6: https://emp.lbl.gov/publications/us-utility-scale-solar-2025-data
A8: Important
A9: These are observed installed-cost benchmarks. Do not treat them as 2030/2035 projections.
A10: The ERCOT wind value is especially useful for diagnosing whether a future wind CAPEX path is too conservative.

Sheet Compare_2030_2035
A1: Harmonized CAPEX Comparison — All Values in Real 2025$/kW
A4: Technology | B4: ERCOT LTSA 2030 | C4: ATB Moderate 2030 | D4: ATB Advanced 2030 | E4: ATB Conservative 2030 | F4: EIA TRE current anchor | G4: NLR BESS Mid 2030 | H4: LBNL empirical anchor | I4: ERCOT LTSA 2035 | J4: ATB Moderate 2035 | K4: ATB Advanced 2035 | L4: ATB Conservative 2035 | M4: NLR BESS Mid 2035 | N4: Interpretation | O4: Recommended Base 2030 | P4: Recommended Base 2035 | Q4: Recommended Base Source
A5: CC multi-shaft | B5: =ERCOT_LTSA_2026!B30 -> 1314.8599 | C5: =NLR_ATB_2024b!K6 -> 1543.7457 | D5: =NLR_ATB_2024b!K5 -> 1519.3508 | E5: =NLR_ATB_2024b!K7 -> 1568.1406 | F5: =EIA_AEO2026_TRE!G6 -> 930 | I5: =ERCOT_LTSA_2026!B35 -> 1254.1144 | J5: =NLR_ATB_2024b!L6 -> 1477.7936 | K5: =NLR_ATB_2024b!L5 -> 1438.0752 | L5: =NLR_ATB_2024b!L7 -> 1517.3894 | N5: Recommended base = ERCOT LTSA; EIA is a lower current regional anchor. | O5: =Recommended_CEM_Base!D4 -> 1314.8599 | P5: =Recommended_CEM_Base!K4 -> 1254.1144 | Q5: =Recommended_CEM_Base!O4 -> ERCOT 2026 LTSA
A6: Advanced CT | B6: =ERCOT_LTSA_2026!C30 -> 1193.778 | C6: =NLR_ATB_2024b!K9 -> 1397.6213 | D6: =NLR_ATB_2024b!K8 -> 1397.6213 | E6: =NLR_ATB_2024b!K10 -> 1397.6213 | F6: =EIA_AEO2026_TRE!G9 -> 1033 | I6: =ERCOT_LTSA_2026!C35 -> 1109.3161 | J6: =NLR_ATB_2024b!L9 -> 1343.6827 | K6: =NLR_ATB_2024b!L8 -> 1343.6827 | L6: =NLR_ATB_2024b!L10 -> 1343.6827 | N6: Recommended base = ERCOT LTSA; compare with EIA industrial-frame CT. | O6: =Recommended_CEM_Base!D5 -> 1193.778 | P6: =Recommended_CEM_Base!K5 -> 1109.3161 | Q6: =Recommended_CEM_Base!O5 -> ERCOT 2026 LTSA
A7: SMR | B7: =ERCOT_LTSA_2026!E30 -> 8608.4759 | C7: =NLR_ATB_2024b!K12 -> 10615.743 | D7: =NLR_ATB_2024b!K11 -> 7058.9076 | E7: =NLR_ATB_2024b!K13 -> 13950.214 | F7: =EIA_AEO2026_TRE!G11 -> 9366 | I7: =ERCOT_LTSA_2026!E35 -> 8133.6439 | J7: =NLR_ATB_2024b!L12 -> 8649.8644 | K7: =NLR_ATB_2024b!L11 -> 4222.7394 | L7: =NLR_ATB_2024b!L13 -> 13259.61 | N7: Recommended central = ERCOT LTSA; retain wide ATB low/high sensitivity. | O7: =Recommended_CEM_Base!D7 -> 8608.4759 | P7: =Recommended_CEM_Base!K7 -> 8133.6439 | Q7: =Recommended_CEM_Base!O7 -> ERCOT 2026 LTSA
A8: Wind | B8: =ERCOT_LTSA_2026!F30 -> 2010.8567 | C8: =NLR_ATB_2024b!K15 -> 1548.8568 | D8: =NLR_ATB_2024b!K14 -> 1475.9427 | E8: =NLR_ATB_2024b!K16 -> 1735.2522 | F8: =EIA_AEO2026_TRE!G13 -> 1562 | H8: =LBNL_Actuals!F5 -> 1447.5189 | I8: =ERCOT_LTSA_2026!F35 -> 1960.4085 | J8: =NLR_ATB_2024b!L15 -> 1468.2638 | K8: =NLR_ATB_2024b!L14 -> 1384.776 | L8: =NLR_ATB_2024b!L16 -> 1674.4837 | N8: Recommended base = ATB Moderate Class 1; ERCOT LTSA = conservative/high planning benchmark. | O8: =Recommended_CEM_Base!D8 -> 1548.8568 | P8: =Recommended_CEM_Base!K8 -> 1468.2638 | Q8: =Recommended_CEM_Base!O8 -> NLR/NREL ATB 2024b Moderate — Wind Class 1
A9: Solar | B9: =ERCOT_LTSA_2026!G30 -> 1171.3554 | C9: =NLR_ATB_2024b!K21 -> 1312.9208 | D9: =NLR_ATB_2024b!K20 -> 1176.6054 | E9: =NLR_ATB_2024b!K22 -> 1501.5365 | F9: =EIA_AEO2026_TRE!G14 -> 1342 | H9: =LBNL_Actuals!F6 -> 1652.3634 | I9: =ERCOT_LTSA_2026!G35 -> 1052.2012 | J9: =NLR_ATB_2024b!L21 -> 984.92209 | K9: =NLR_ATB_2024b!L20 -> 751.23849 | L9: =NLR_ATB_2024b!L22 -> 1308.2632 | N9: Recommended base = ERCOT LTSA; source disagreement is comparatively modest. | O9: =Recommended_CEM_Base!D9 -> 1171.3554 | P9: =Recommended_CEM_Base!K9 -> 1052.2012 | Q9: =Recommended_CEM_Base!O9 -> ERCOT 2026 LTSA
A10: BESS 2h | B10: =ERCOT_LTSA_2026!H30 -> 697.79061 | C10: =NLR_ATB_2024b!K24 -> 1036.2456 | D10: =NLR_ATB_2024b!K23 -> 776.74218 | E10: =NLR_ATB_2024b!K25 -> 1225.9949 | I10: =ERCOT_LTSA_2026!H35 -> 645.15699 | J10: =NLR_ATB_2024b!L24 -> 972.84687 | K10: =NLR_ATB_2024b!L23 -> 718.12139 | L10: =NLR_ATB_2024b!L25 -> 1187.9279 | N10: Recommended base = ERCOT LTSA; alternate duration, while 4h remains the preferred core storage case. | O10: =Recommended_CEM_Base!D10 -> 697.79061 | P10: =Recommended_CEM_Base!K10 -> 645.15699 | Q10: =Recommended_CEM_Base!O10 -> ERCOT 2026 LTSA
A11: BESS 4h | B11: =ERCOT_LTSA_2026!I30 -> 1200.9532 | C11: =NLR_ATB_2024b!K27 -> 1596.5588 | D11: =NLR_ATB_2024b!K26 -> 1229.4452 | E11: =NLR_ATB_2024b!K28 -> 1952.5427 | F11: =EIA_AEO2026_TRE!G12 -> 1500 | G11: =NLR_BESS_2025!I11 -> 1145.365 | I11: =ERCOT_LTSA_2026!I35 -> 1110.9249 | J11: =NLR_ATB_2024b!L27 -> 1482.2396 | K11: =NLR_ATB_2024b!L26 -> 1131.662 | L11: =NLR_ATB_2024b!L28 -> 1889.6032 | M11: =NLR_BESS_2025!I16 -> 997.57593 | N11: Recommended base = NLR 2025 Mid; use NLR Low/High as the primary battery sensitivities. | O11: =Recommended_CEM_Base!D11 -> 1145.365 | P11: =Recommended_CEM_Base!K11 -> 997.57593 | Q11: =Recommended_CEM_Base!O11 -> NLR 2025 Utility-Scale Battery Storage — Mid
A12: BESS 6h | B12: =ERCOT_LTSA_2026!J30 -> 1705.0128 | C12: =NLR_ATB_2024b!K30 -> 2156.8719 | D12: =NLR_ATB_2024b!K29 -> 1682.1483 | E12: =NLR_ATB_2024b!K31 -> 2679.0906 | I12: =ERCOT_LTSA_2026!J35 -> 1576.6929 | J12: =NLR_ATB_2024b!L30 -> 1991.6324 | K12: =NLR_ATB_2024b!L29 -> 1545.2026 | L12: =NLR_ATB_2024b!L31 -> 2591.2784 | N12: Recommended base = ERCOT LTSA; alternate duration, while 4h remains the preferred core storage case. | O12: =Recommended_CEM_Base!D12 -> 1705.0128 | P12: =Recommended_CEM_Base!K12 -> 1576.6929 | Q12: =Recommended_CEM_Base!O12 -> ERCOT 2026 LTSA
A13: Diesel backup generator | N13: Standby/resilience generator; lower CAPEX but not intended as the utility-scale peaker representation. | O13: =Recommended_CEM_Base!D13 -> 800 | P13: =Recommended_CEM_Base!K13 -> 800 | Q13: Backup-generator synthesis (NREL / EDF / BofA / MIT)
A14: Diesel peaker plant | N14: Grid-connected peaker; EIA Texas engineering benchmark used as central CAPEX with current petroleum-liquid construction costs as a lower empirical check. | O14: =Recommended_CEM_Base!D15 -> 1373.8713 | P14: =Recommended_CEM_Base!K15 -> 1373.8713 | Q14: EIA/S&L Texas 20-MW ICE engineering benchmark
A16: How to read this table
A17: The recommended base is technology-specific; see columns O:Q and Recommended_CEM_Base. ERCOT LTSA is not treated as the central source for every technology.
A18: EIA TRE is a current regional anchor, not an explicit 2030/2035 forecast. LBNL is an empirical historical calibration.
A19: Diesel backup and diesel peaker are intentionally separate because their installed-system scope and use case differ materially.

Sheet CEM_BaseCase
A1: ERCOT LTSA Benchmark + External Diesel Assumptions — 2030 / 2035 (Real 2025$)
A2: Benchmark tab: ERCOT LTSA CAPEX is used for technologies covered by LTSA. Diesel is shown separately as (1) backup generator and (2) utility-scale peaker because LTSA does not provide diesel-specific series.
A3: Technology | B3: Economic life (yr) | C3: Real WACC | D3: 2030 CAPEX (2025$/kW) | E3: CRF | F3: 2030 annualized CAPEX (2025$/kW-yr) | G3: 2030 FOM (2025$/kW-yr) | H3: 2030 total fixed (2025$/kW-yr) | I3: VOM (2025$/MWh) | J3: Heat rate (Btu/kWh) | K3: 2035 CAPEX (2025$/kW) | L3: 2035 annualized CAPEX (2025$/kW-yr) | M3: 2035 FOM (2025$/kW-yr) | N3: 2035 total fixed (2025$/kW-yr) | O3: CAPEX source | P3: O&M source | Q3: Modeling note
A4: CC multi-shaft | B4: =Assumptions!B15 -> 30 | C4: =Assumptions!$B$5 -> 0.07 | D4: =ERCOT_LTSA_2026!B30 -> 1314.8599 | E4: =C4*(1+C4)^B4/((1+C4)^B4-1) -> 0.080586404 | F4: =D4*E4 -> 105.95983 | G4: =EIA_AEO2026_TRE!H6 -> 12.69 | H4: =F4+IF(G4="",0,G4) -> 118.64983 | I4: =EIA_AEO2026_TRE!I6 -> 3.57 | J4: =EIA_AEO2026_TRE!J6 -> 6226 | K4: =ERCOT_LTSA_2026!B35 -> 1254.1144 | L4: =K4*E4 -> 101.06457 | M4: =EIA_AEO2026_TRE!H6 -> 12.69 | N4: =L4+IF(M4="",0,M4) -> 113.75457 | O4: ERCOT 2026 LTSA | P4: EIA AEO2026; held constant in real 2025$ unless changed | Q4: Base CAPEX = ERCOT LTSA; O&M/performance = EIA multi-shaft CC.
A5: Advanced CT | B5: =Assumptions!B16 -> 30 | C5: =Assumptions!$B$5 -> 0.07 | D5: =ERCOT_LTSA_2026!C30 -> 1193.778 | E5: =C5*(1+C5)^B5/((1+C5)^B5-1) -> 0.080586404 | F5: =D5*E5 -> 96.202277 | G5: =EIA_AEO2026_TRE!H9 -> 7.18 | H5: =F5+IF(G5="",0,G5) -> 103.38228 | I5: =EIA_AEO2026_TRE!I9 -> 4.17 | J5: =EIA_AEO2026_TRE!J9 -> 9142 | K5: =ERCOT_LTSA_2026!C35 -> 1109.3161 | L5: =K5*E5 -> 89.395793 | M5: =EIA_AEO2026_TRE!H9 -> 7.18 | N5: =L5+IF(M5="",0,M5) -> 96.575793 | O5: ERCOT 2026 LTSA | P5: EIA AEO2026; held constant in real 2025$ unless changed | Q5: Base CAPEX = ERCOT LTSA; O&M/performance = EIA industrial-frame CT.
A6: ICE | B6: =Assumptions!B17 -> 30 | C6: =Assumptions!$B$5 -> 0.07 | D6: =ERCOT_LTSA_2026!D30 -> 2102.3408 | E6: =C6*(1+C6)^B6/((1+C6)^B6-1) -> 0.080586404 | F6: =D6*E6 -> 169.42009 | H6: =F6+IF(G6="",0,G6) -> 169.42009 | K6: =ERCOT_LTSA_2026!D35 -> 2036.8298 | L6: =K6*E6 -> 164.14079 | N6: =L6+IF(M6="",0,M6) -> 164.14079 | O6: ERCOT 2026 LTSA | P6: Not populated — add engine-specific O&M/performance source | Q6: ERCOT CAPEX is available, but O&M/heat rate should come from the engine technology selected in the model.
A7: SMR | B7: =Assumptions!B18 -> 60 | C7: =Assumptions!$B$5 -> 0.07 | D7: =ERCOT_LTSA_2026!E30 -> 8608.4759 | E7: =C7*(1+C7)^B7/((1+C7)^B7-1) -> 0.071229226 | F7: =D7*E7 -> 613.17507 | G7: =EIA_AEO2026_TRE!H11 -> 127.62 | H7: =F7+IF(G7="",0,G7) -> 740.79507 | I7: =EIA_AEO2026_TRE!I11 -> 3.32 | J7: =EIA_AEO2026_TRE!J11 -> 10445 | K7: =ERCOT_LTSA_2026!E35 -> 8133.6439 | L7: =K7*E7 -> 579.35315 | M7: =EIA_AEO2026_TRE!H11 -> 127.62 | N7: =L7+IF(M7="",0,M7) -> 706.97315 | O7: ERCOT 2026 LTSA | P7: EIA AEO2026; held constant in real 2025$ unless changed | Q7: Large uncertainty; retain ATB Advanced/Moderate/Conservative sensitivities.
A8: Wind | B8: =Assumptions!B19 -> 30 | C8: =Assumptions!$B$5 -> 0.07 | D8: =ERCOT_LTSA_2026!F30 -> 2010.8567 | E8: =C8*(1+C8)^B8/((1+C8)^B8-1) -> 0.080586404 | F8: =D8*E8 -> 162.04771 | G8: =EIA_AEO2026_TRE!H13 -> 34.57 | H8: =F8+IF(G8="",0,G8) -> 196.61771 | I8: =EIA_AEO2026_TRE!I13 -> 0 | K8: =ERCOT_LTSA_2026!F35 -> 1960.4085 | L8: =K8*E8 -> 157.98227 | M8: =EIA_AEO2026_TRE!H13 -> 34.57 | N8: =L8+IF(M8="",0,M8) -> 192.55227 | O8: ERCOT 2026 LTSA | P8: EIA AEO2026; held constant in real 2025$ unless changed | Q8: Use ERCOT LTSA base, but compare with ATB and LBNL ERCOT actual costs.
A9: Solar | B9: =Assumptions!B20 -> 30 | C9: =Assumptions!$B$5 -> 0.07 | D9: =ERCOT_LTSA_2026!G30 -> 1171.3554 | E9: =C9*(1+C9)^B9/((1+C9)^B9-1) -> 0.080586404 | F9: =D9*E9 -> 94.395322 | G9: =EIA_AEO2026_TRE!H14 -> 23.6 | H9: =F9+IF(G9="",0,G9) -> 117.99532 | I9: =EIA_AEO2026_TRE!I14 -> 0 | K9: =ERCOT_LTSA_2026!G35 -> 1052.2012 | L9: =K9*E9 -> 84.793109 | M9: =EIA_AEO2026_TRE!H14 -> 23.6 | N9: =L9+IF(M9="",0,M9) -> 108.39311 | O9: ERCOT 2026 LTSA | P9: EIA AEO2026; held constant in real 2025$ unless changed | Q9: Use ERCOT LTSA base; EIA/LBNL provide useful current-cost checks.
A10: BESS 2h | B10: =Assumptions!B21 -> 15 | C10: =Assumptions!$B$5 -> 0.07 | D10: =ERCOT_LTSA_2026!H30 -> 697.79061 | E10: =C10*(1+C10)^B10/((1+C10)^B10-1) -> 0.10979462 | F10: =D10*E10 -> 76.613658 | G10: =NLR_ATB_2024b!M24 -> 22.242684 | H10: =F10+IF(G10="",0,G10) -> 98.856342 | I10: =NLR_ATB_2024b!O24 -> 0 | K10: =ERCOT_LTSA_2026!H35 -> 645.15699 | L10: =K10*E10 -> 70.83477 | M10: =NLR_ATB_2024b!N24 -> 20.713591 | N10: =L10+IF(M10="",0,M10) -> 91.548361 | O10: ERCOT 2026 LTSA | P10: NLR/NREL ATB Moderate duration-specific O&M | Q10: ERCOT LTSA CAPEX + ATB Moderate duration-specific FOM/VOM.
A11: BESS 4h | B11: =Assumptions!B22 -> 15 | C11: =Assumptions!$B$5 -> 0.07 | D11: =ERCOT_LTSA_2026!I30 -> 1200.9532 | E11: =C11*(1+C11)^B11/((1+C11)^B11-1) -> 0.10979462 | F11: =D11*E11 -> 131.85821 | G11: =NLR_ATB_2024b!M27 -> 35.756699 | H11: =F11+IF(G11="",0,G11) -> 167.61491 | I11: =NLR_ATB_2024b!O27 -> 0 | K11: =ERCOT_LTSA_2026!I35 -> 1110.9249 | L11: =K11*E11 -> 121.97359 | M11: =NLR_ATB_2024b!N27 -> 32.999473 | N11: =L11+IF(M11="",0,M11) -> 154.97306 | O11: ERCOT 2026 LTSA | P11: NLR/NREL ATB Moderate duration-specific O&M | Q11: ERCOT LTSA CAPEX + ATB Moderate O&M; newer NLR battery series is a key sensitivity.
A12: BESS 6h | B12: =Assumptions!B23 -> 15 | C12: =Assumptions!$B$5 -> 0.07 | D12: =ERCOT_LTSA_2026!J30 -> 1705.0128 | E12: =C12*(1+C12)^B12/((1+C12)^B12-1) -> 0.10979462 | F12: =D12*E12 -> 187.20124 | G12: =NLR_ATB_2024b!M30 -> 49.270714 | H12: =F12+IF(G12="",0,G12) -> 236.47195 | I12: =NLR_ATB_2024b!O30 -> 0 | K12: =ERCOT_LTSA_2026!J35 -> 1576.6929 | L12: =K12*E12 -> 173.11241 | M12: =NLR_ATB_2024b!N30 -> 45.285354 | N12: =L12+IF(M12="",0,M12) -> 218.39776 | O12: ERCOT 2026 LTSA | P12: NLR/NREL ATB Moderate duration-specific O&M | Q12: ERCOT LTSA CAPEX + ATB Moderate duration-specific FOM/VOM.
A13: Diesel backup generator | B13: =Assumptions!B24 -> 20 | C13: =Assumptions!$B$5 -> 0.07 | D13: =Diesel_Review!B20 -> 800 | E13: =C13*(1+C13)^B13/((1+C13)^B13-1) -> 0.094392926 | F13: =D13*E13 -> 75.514341 | G13: =Diesel_Review!D20 -> 35 | H13: =F13+G13 -> 110.51434 | I13: =Diesel_Review!E20 -> 0 | J13: =Diesel_Review!F20*1000 -> 9500 | K13: =Diesel_Review!C20 -> 800 | L13: =K13*E13 -> 75.514341 | M13: =Diesel_Review!D20 -> 35 | N13: =L13+M13 -> 110.51434 | O13: Backup-generator synthesis (not ERCOT LTSA) | P13: EDF 2024 / diesel review | Q13: Standby/resilience case; not the utility-scale peaker assumption.
A14: Diesel peaker plant | B14: =Assumptions!B25 -> 30 | C14: =Assumptions!$B$5 -> 0.07 | D14: =Diesel_Review!B21 -> 1373.8713 | E14: =C14*(1+C14)^B14/((1+C14)^B14-1) -> 0.080586404 | F14: =D14*E14 -> 110.71535 | G14: =Diesel_Review!D21 -> 44.276182 | H14: =F14+G14 -> 154.99153 | I14: =Diesel_Review!E21 -> 7.1652866 | J14: =Diesel_Review!F21*1000 -> 9500 | K14: =Diesel_Review!C21 -> 1373.8713 | L14: =K14*E14 -> 110.71535 | M14: =Diesel_Review!D21 -> 44.276182 | N14: =L14+M14 -> 154.99153 | O14: EIA/S&L Texas utility-scale ICE benchmark | P14: EIA/S&L engine-plant O&M proxy | Q14: Grid-connected liquid-fuel peaker; separate from backup generator.
A16: Annualization method
A17: CRF = r(1+r)^n / [(1+r)^n - 1]. Annualized CAPEX = real-2025$ CAPEX × CRF. Total fixed = annualized CAPEX + FOM.
A18: The 7% real WACC and economic lives are editable assumptions on the Assumptions sheet; they are not source facts.

Sheet HOPE_CostProfiles
A1: HOPE-Compatible ERCOT Candidate Cost Profiles — Recommended Hybrid Base
A2: Columns A:U follow the current HOPE candidate_resource_costs_2035.csv schema. Fixed costs now link to Recommended_CEM_Base (technology-specific source selection). Thermal/nuclear fuel-price cells remain editable because fuel price is separate from capital-cost selection.
A4: Type | B4: ApplyToExistingCandidates | C4: CostDollarPerMWYr | D4: CostDollarPerMWh | E4: CapexDollarPerKW | F4: FixedOMDollarPerKWYr | G4: RealDiscountRate | H4: FixedChargeRate | I4: EconomicLifeYears | J4: ProjectionYear | K4: ATBDollarYear | L4: TargetDollarYear | M4: CPIConversionFactor | N4: ATBTechnology | O4: ATBTechDetail | P4: ATBScenario | Q4: ATBFinancialCase | R4: FuelPriceDollarPerMMBtu | S4: HeatRateMMBtuPerMWh | T4: SourceURL | U4: SourceNote | V4: DurationHours [helper] | W4: ReadyForDirectHOPE [helper] | X4: VariableCostStatus [helper]
A5: NGCC | B5: 1 | C5: =IF(F5="","",Recommended_CEM_Base!H4*1000) -> 118649.83 | D5: =IF(OR(R5="",S5=""),"",Recommended_CEM_Base!I4+R5*S5) | E5: =Recommended_CEM_Base!D4 -> 1314.8599 | F5: =IF(Recommended_CEM_Base!G4="","",Recommended_CEM_Base!G4) -> 12.69 | G5: =Recommended_CEM_Base!C4 -> 0.07 | H5: =Recommended_CEM_Base!E4 -> 0.080586404 | I5: =Recommended_CEM_Base!B4 -> 30 | J5: 2030 | L5: 2025 | M5: 1 | N5: Recommended hybrid | O5: NGCC | P5: Technology-specific base | Q5: 7% real CRF | S5: =IF(Recommended_CEM_Base!J4="","",Recommended_CEM_Base!J4/1000) -> 6.226 | T5: https://github.com/swang22/PJM_DC_health_study_project/blob/main/scenario_assumptions/candidate_resource_costs_2035.csv | U5: Linked to Recommended_CEM_Base. CAPEX source = ERCOT LTSA. Enter fuel price in column R before direct run; variable cost = VOM + fuel × heat rate. | W5: =IF(COUNT(C5:F5)=4,"YES","NO") -> NO | X5: =IF(F5="","FOM needed",IF(OR(R5="",S5=""),"Fuel price / heat rate needed","Ready")) -> Fuel price / heat rate needed
A6: NGCT | B6: 1 | C6: =IF(F6="","",Recommended_CEM_Base!H5*1000) -> 103382.28 | D6: =IF(OR(R6="",S6=""),"",Recommended_CEM_Base!I5+R6*S6) | E6: =Recommended_CEM_Base!D5 -> 1193.778 | F6: =IF(Recommended_CEM_Base!G5="","",Recommended_CEM_Base!G5) -> 7.18 | G6: =Recommended_CEM_Base!C5 -> 0.07 | H6: =Recommended_CEM_Base!E5 -> 0.080586404 | I6: =Recommended_CEM_Base!B5 -> 30 | J6: 2030 | L6: 2025 | M6: 1 | N6: Recommended hybrid | O6: NGCT | P6: Technology-specific base | Q6: 7% real CRF | S6: =IF(Recommended_CEM_Base!J5="","",Recommended_CEM_Base!J5/1000) -> 9.142 | T6: https://github.com/swang22/PJM_DC_health_study_project/blob/main/scenario_assumptions/candidate_resource_costs_2035.csv | U6: Linked to Recommended_CEM_Base. CAPEX source = ERCOT LTSA. Enter fuel price in column R before direct run; variable cost = VOM + fuel × heat rate. | W6: =IF(COUNT(C6:F6)=4,"YES","NO") -> NO | X6: =IF(F6="","FOM needed",IF(OR(R6="",S6=""),"Fuel price / heat rate needed","Ready")) -> Fuel price / heat rate needed
A7: ICE | B7: 1 | C7: =IF(F7="","",Recommended_CEM_Base!H6*1000) | D7: =IF(OR(R7="",S7=""),"",Recommended_CEM_Base!I6+R7*S7) | E7: =Recommended_CEM_Base!D6 -> 2102.3408 | F7: =IF(Recommended_CEM_Base!G6="","",Recommended_CEM_Base!G6) | G7: =Recommended_CEM_Base!C6 -> 0.07 | H7: =Recommended_CEM_Base!E6 -> 0.080586404 | I7: =Recommended_CEM_Base!B6 -> 30 | J7: 2030 | L7: 2025 | M7: 1 | N7: Recommended hybrid | O7: ICE | P7: Technology-specific base | Q7: 7% real CRF | S7: =IF(Recommended_CEM_Base!J6="","",Recommended_CEM_Base!J6/1000) | T7: https://github.com/swang22/PJM_DC_health_study_project/blob/main/scenario_assumptions/candidate_resource_costs_2035.csv | U7: Linked to Recommended_CEM_Base. CAPEX source = ERCOT LTSA. Enter fuel price in column R before direct run; variable cost = VOM + fuel × heat rate. | W7: =IF(COUNT(C7:F7)=4,"YES","NO") -> NO | X7: =IF(F7="","FOM needed",IF(OR(R7="",S7=""),"Fuel price / heat rate needed","Ready")) -> FOM needed
A8: NuC | B8: 1 | C8: =IF(F8="","",Recommended_CEM_Base!H7*1000) -> 740795.07 | D8: =IF(OR(R8="",S8=""),"",Recommended_CEM_Base!I7+R8*S8) | E8: =Recommended_CEM_Base!D7 -> 8608.4759 | F8: =IF(Recommended_CEM_Base!G7="","",Recommended_CEM_Base!G7) -> 127.62 | G8: =Recommended_CEM_Base!C7 -> 0.07 | H8: =Recommended_CEM_Base!E7 -> 0.071229226 | I8: =Recommended_CEM_Base!B7 -> 60 | J8: 2030 | L8: 2025 | M8: 1 | N8: Recommended hybrid | O8: NuC | P8: Technology-specific base | Q8: 7% real CRF | S8: =IF(Recommended_CEM_Base!J7="","",Recommended_CEM_Base!J7/1000) -> 10.445 | T8: https://github.com/swang22/PJM_DC_health_study_project/blob/main/scenario_assumptions/candidate_resource_costs_2035.csv | U8: Linked to Recommended_CEM_Base. CAPEX source = ERCOT LTSA central + ATB sensitivity. Enter fuel price in column R before direct run; variable cost = VOM + fuel × heat rate. | W8: =IF(COUNT(C8:F8)=4,"YES","NO") -> NO | X8: =IF(F8="","FOM needed",IF(OR(R8="",S8=""),"Fuel price / heat rate needed","Ready")) -> Fuel price / heat rate needed
A9: WindOn | B9: 0 | C9: =IF(F9="","",Recommended_CEM_Base!H8*1000) -> 157009.2 | D9: =Recommended_CEM_Base!I8 -> 0 | E9: =Recommended_CEM_Base!D8 -> 1548.8568 | F9: =IF(Recommended_CEM_Base!G8="","",Recommended_CEM_Base!G8) -> 32.1924 | G9: =Recommended_CEM_Base!C8 -> 0.07 | H9: =Recommended_CEM_Base!E8 -> 0.080586404 | I9: =Recommended_CEM_Base!B8 -> 30 | J9: 2030 | L9: 2025 | M9: 1 | N9: Recommended hybrid | O9: WindOn | P9: Technology-specific base | Q9: 7% real CRF | R9: 0 | S9: 0 | T9: https://github.com/swang22/PJM_DC_health_study_project/blob/main/scenario_assumptions/candidate_resource_costs_2035.csv | U9: Linked to Recommended_CEM_Base. CAPEX source = ATB Moderate Wind Class 1. Variable cost uses the recommended-sheet VOM. | W9: =IF(COUNT(C9:F9)=4,"YES","NO") -> YES | X9: =IF(F9="","FOM needed","Ready") -> Ready
A10: SolarPV | B10: 0 | C10: =IF(F10="","",Recommended_CEM_Base!H9*1000) -> 117995.32 | D10: =Recommended_CEM_Base!I9 -> 0 | E10: =Recommended_CEM_Base!D9 -> 1171.3554 | F10: =IF(Recommended_CEM_Base!G9="","",Recommended_CEM_Base!G9) -> 23.6 | G10: =Recommended_CEM_Base!C9 -> 0.07 | H10: =Recommended_CEM_Base!E9 -> 0.080586404 | I10: =Recommended_CEM_Base!B9 -> 30 | J10: 2030 | L10: 2025 | M10: 1 | N10: Recommended hybrid | O10: SolarPV | P10: Technology-specific base | Q10: 7% real CRF | R10: 0 | S10: 0 | T10: https://github.com/swang22/PJM_DC_health_study_project/blob/main/scenario_assumptions/candidate_resource_costs_2035.csv | U10: Linked to Recommended_CEM_Base. CAPEX source = ERCOT LTSA. Variable cost uses the recommended-sheet VOM. | W10: =IF(COUNT(C10:F10)=4,"YES","NO") -> YES | X10: =IF(F10="","FOM needed","Ready") -> Ready
A11: Battery | B11: 0 | C11: =IF(F11="","",Recommended_CEM_Base!H10*1000) -> 98856.342 | D11: =Recommended_CEM_Base!I10 -> 0 | E11: =Recommended_CEM_Base!D10 -> 697.79061 | F11: =IF(Recommended_CEM_Base!G10="","",Recommended_CEM_Base!G10) -> 22.242684 | G11: =Recommended_CEM_Base!C10 -> 0.07 | H11: =Recommended_CEM_Base!E10 -> 0.10979462 | I11: =Recommended_CEM_Base!B10 -> 15 | J11: 2030 | L11: 2025 | M11: 1 | N11: Recommended hybrid | O11: Battery_2h | P11: Technology-specific base | Q11: 7% real CRF | R11: 0 | S11: 0 | T11: https://github.com/swang22/PJM_DC_health_study_project/blob/main/scenario_assumptions/candidate_resource_costs_2035.csv | U11: Linked to Recommended_CEM_Base. CAPEX source = ERCOT LTSA. Variable cost uses the recommended-sheet VOM. Current HOPE generic storage setup uses 4-hour storage. | V11: 2 | W11: =IF(COUNT(C11:F11)=4,"YES","NO") -> YES | X11: =IF(F11="","FOM needed","Ready") -> Ready
A12: Battery | B12: 1 | C12: =IF(F12="","",Recommended_CEM_Base!H11*1000) -> 161511.61 | D12: =Recommended_CEM_Base!I11 -> 0 | E12: =Recommended_CEM_Base!D11 -> 1145.365 | F12: =IF(Recommended_CEM_Base!G11="","",Recommended_CEM_Base!G11) -> 35.756699 | G12: =Recommended_CEM_Base!C11 -> 0.07 | H12: =Recommended_CEM_Base!E11 -> 0.10979462 | I12: =Recommended_CEM_Base!B11 -> 15 | J12: 2030 | L12: 2025 | M12: 1 | N12: Recommended hybrid | O12: Battery_4h | P12: Technology-specific base | Q12: 7% real CRF | R12: 0 | S12: 0 | T12: https://github.com/swang22/PJM_DC_health_study_project/blob/main/scenario_assumptions/candidate_resource_costs_2035.csv | U12: Linked to Recommended_CEM_Base. CAPEX source = NLR 2025 Mid. Variable cost uses the recommended-sheet VOM. | V12: 4 | W12: =IF(COUNT(C12:F12)=4,"YES","NO") -> YES | X12: =IF(F12="","FOM needed","Ready") -> Ready
A13: Battery | B13: 0 | C13: =IF(F13="","",Recommended_CEM_Base!H12*1000) -> 236471.95 | D13: =Recommended_CEM_Base!I12 -> 0 | E13: =Recommended_CEM_Base!D12 -> 1705.0128 | F13: =IF(Recommended_CEM_Base!G12="","",Recommended_CEM_Base!G12) -> 49.270714 | G13: =Recommended_CEM_Base!C12 -> 0.07 | H13: =Recommended_CEM_Base!E12 -> 0.10979462 | I13: =Recommended_CEM_Base!B12 -> 15 | J13: 2030 | L13: 2025 | M13: 1 | N13: Recommended hybrid | O13: Battery_6h | P13: Technology-specific base | Q13: 7% real CRF | R13: 0 | S13: 0 | T13: https://github.com/swang22/PJM_DC_health_study_project/blob/main/scenario_assumptions/candidate_resource_costs_2035.csv | U13: Linked to Recommended_CEM_Base. CAPEX source = ERCOT LTSA. Variable cost uses the recommended-sheet VOM. Current HOPE generic storage setup uses 4-hour storage. | V13: 6 | W13: =IF(COUNT(C13:F13)=4,"YES","NO") -> YES | X13: =IF(F13="","FOM needed","Ready") -> Ready
A14: NGCC | B14: 1 | C14: =IF(F14="","",Recommended_CEM_Base!N4*1000) -> 113754.57 | D14: =IF(OR(R14="",S14=""),"",Recommended_CEM_Base!I4+R14*S14) | E14: =Recommended_CEM_Base!K4 -> 1254.1144 | F14: =IF(Recommended_CEM_Base!M4="","",Recommended_CEM_Base!M4) -> 12.69 | G14: =Recommended_CEM_Base!C4 -> 0.07 | H14: =Recommended_CEM_Base!E4 -> 0.080586404 | I14: =Recommended_CEM_Base!B4 -> 30 | J14: 2035 | L14: 2025 | M14: 1 | N14: Recommended hybrid | O14: NGCC | P14: Technology-specific base | Q14: 7% real CRF | S14: =IF(Recommended_CEM_Base!J4="","",Recommended_CEM_Base!J4/1000) -> 6.226 | T14: https://github.com/swang22/PJM_DC_health_study_project/blob/main/scenario_assumptions/candidate_resource_costs_2035.csv | U14: Linked to Recommended_CEM_Base. CAPEX source = ERCOT LTSA. Enter fuel price in column R before direct run; variable cost = VOM + fuel × heat rate. | W14: =IF(COUNT(C14:F14)=4,"YES","NO") -> NO | X14: =IF(F14="","FOM needed",IF(OR(R14="",S14=""),"Fuel price / heat rate needed","Ready")) -> Fuel price / heat rate needed
A15: NGCT | B15: 1 | C15: =IF(F15="","",Recommended_CEM_Base!N5*1000) -> 96575.793 | D15: =IF(OR(R15="",S15=""),"",Recommended_CEM_Base!I5+R15*S15) | E15: =Recommended_CEM_Base!K5 -> 1109.3161 | F15: =IF(Recommended_CEM_Base!M5="","",Recommended_CEM_Base!M5) -> 7.18 | G15: =Recommended_CEM_Base!C5 -> 0.07 | H15: =Recommended_CEM_Base!E5 -> 0.080586404 | I15: =Recommended_CEM_Base!B5 -> 30 | J15: 2035 | L15: 2025 | M15: 1 | N15: Recommended hybrid | O15: NGCT | P15: Technology-specific base | Q15: 7% real CRF | S15: =IF(Recommended_CEM_Base!J5="","",Recommended_CEM_Base!J5/1000) -> 9.142 | T15: https://github.com/swang22/PJM_DC_health_study_project/blob/main/scenario_assumptions/candidate_resource_costs_2035.csv | U15: Linked to Recommended_CEM_Base. CAPEX source = ERCOT LTSA. Enter fuel price in column R before direct run; variable cost = VOM + fuel × heat rate. | W15: =IF(COUNT(C15:F15)=4,"YES","NO") -> NO | X15: =IF(F15="","FOM needed",IF(OR(R15="",S15=""),"Fuel price / heat rate needed","Ready")) -> Fuel price / heat rate needed
A16: ICE | B16: 1 | C16: =IF(F16="","",Recommended_CEM_Base!N6*1000) | D16: =IF(OR(R16="",S16=""),"",Recommended_CEM_Base!I6+R16*S16) | E16: =Recommended_CEM_Base!K6 -> 2036.8298 | F16: =IF(Recommended_CEM_Base!M6="","",Recommended_CEM_Base!M6) | G16: =Recommended_CEM_Base!C6 -> 0.07 | H16: =Recommended_CEM_Base!E6 -> 0.080586404 | I16: =Recommended_CEM_Base!B6 -> 30 | J16: 2035 | L16: 2025 | M16: 1 | N16: Recommended hybrid | O16: ICE | P16: Technology-specific base | Q16: 7% real CRF | S16: =IF(Recommended_CEM_Base!J6="","",Recommended_CEM_Base!J6/1000) | T16: https://github.com/swang22/PJM_DC_health_study_project/blob/main/scenario_assumptions/candidate_resource_costs_2035.csv | U16: Linked to Recommended_CEM_Base. CAPEX source = ERCOT LTSA. Enter fuel price in column R before direct run; variable cost = VOM + fuel × heat rate. | W16: =IF(COUNT(C16:F16)=4,"YES","NO") -> NO | X16: =IF(F16="","FOM needed",IF(OR(R16="",S16=""),"Fuel price / heat rate needed","Ready")) -> FOM needed
A17: NuC | B17: 1 | C17: =IF(F17="","",Recommended_CEM_Base!N7*1000) -> 706973.15 | D17: =IF(OR(R17="",S17=""),"",Recommended_CEM_Base!I7+R17*S17) | E17: =Recommended_CEM_Base!K7 -> 8133.6439 | F17: =IF(Recommended_CEM_Base!M7="","",Recommended_CEM_Base!M7) -> 127.62 | G17: =Recommended_CEM_Base!C7 -> 0.07 | H17: =Recommended_CEM_Base!E7 -> 0.071229226 | I17: =Recommended_CEM_Base!B7 -> 60 | J17: 2035 | L17: 2025 | M17: 1 | N17: Recommended hybrid | O17: NuC | P17: Technology-specific base | Q17: 7% real CRF | S17: =IF(Recommended_CEM_Base!J7="","",Recommended_CEM_Base!J7/1000) -> 10.445 | T17: https://github.com/swang22/PJM_DC_health_study_project/blob/main/scenario_assumptions/candidate_resource_costs_2035.csv | U17: Linked to Recommended_CEM_Base. CAPEX source = ERCOT LTSA central + ATB sensitivity. Enter fuel price in column R before direct run; variable cost = VOM + fuel × heat rate. | W17: =IF(COUNT(C17:F17)=4,"YES","NO") -> NO | X17: =IF(F17="","FOM needed",IF(OR(R17="",S17=""),"Fuel price / heat rate needed","Ready")) -> Fuel price / heat rate needed
A18: WindOn | B18: 0 | C18: =IF(F18="","",Recommended_CEM_Base!N8*1000) -> 149411.61 | D18: =Recommended_CEM_Base!I8 -> 0 | E18: =Recommended_CEM_Base!K8 -> 1468.2638 | F18: =IF(Recommended_CEM_Base!M8="","",Recommended_CEM_Base!M8) -> 31.089513 | G18: =Recommended_CEM_Base!C8 -> 0.07 | H18: =Recommended_CEM_Base!E8 -> 0.080586404 | I18: =Recommended_CEM_Base!B8 -> 30 | J18: 2035 | L18: 2025 | M18: 1 | N18: Recommended hybrid | O18: WindOn | P18: Technology-specific base | Q18: 7% real CRF | R18: 0 | S18: 0 | T18: https://github.com/swang22/PJM_DC_health_study_project/blob/main/scenario_assumptions/candidate_resource_costs_2035.csv | U18: Linked to Recommended_CEM_Base. CAPEX source = ATB Moderate Wind Class 1. Variable cost uses the recommended-sheet VOM. | W18: =IF(COUNT(C18:F18)=4,"YES","NO") -> YES | X18: =IF(F18="","FOM needed","Ready") -> Ready
A19: SolarPV | B19: 0 | C19: =IF(F19="","",Recommended_CEM_Base!N9*1000) -> 108393.11 | D19: =Recommended_CEM_Base!I9 -> 0 | E19: =Recommended_CEM_Base!K9 -> 1052.2012 | F19: =IF(Recommended_CEM_Base!M9="","",Recommended_CEM_Base!M9) -> 23.6 | G19: =Recommended_CEM_Base!C9 -> 0.07 | H19: =Recommended_CEM_Base!E9 -> 0.080586404 | I19: =Recommended_CEM_Base!B9 -> 30 | J19: 2035 | L19: 2025 | M19: 1 | N19: Recommended hybrid | O19: SolarPV | P19: Technology-specific base | Q19: 7% real CRF | R19: 0 | S19: 0 | T19: https://github.com/swang22/PJM_DC_health_study_project/blob/main/scenario_assumptions/candidate_resource_costs_2035.csv | U19: Linked to Recommended_CEM_Base. CAPEX source = ERCOT LTSA. Variable cost uses the recommended-sheet VOM. | W19: =IF(COUNT(C19:F19)=4,"YES","NO") -> YES | X19: =IF(F19="","FOM needed","Ready") -> Ready
A20: Battery | B20: 0 | C20: =IF(F20="","",Recommended_CEM_Base!N10*1000) -> 91548.361 | D20: =Recommended_CEM_Base!I10 -> 0 | E20: =Recommended_CEM_Base!K10 -> 645.15699 | F20: =IF(Recommended_CEM_Base!M10="","",Recommended_CEM_Base!M10) -> 20.713591 | G20: =Recommended_CEM_Base!C10 -> 0.07 | H20: =Recommended_CEM_Base!E10 -> 0.10979462 | I20: =Recommended_CEM_Base!B10 -> 15 | J20: 2035 | L20: 2025 | M20: 1 | N20: Recommended hybrid | O20: Battery_2h | P20: Technology-specific base | Q20: 7% real CRF | R20: 0 | S20: 0 | T20: https://github.com/swang22/PJM_DC_health_study_project/blob/main/scenario_assumptions/candidate_resource_costs_2035.csv | U20: Linked to Recommended_CEM_Base. CAPEX source = ERCOT LTSA. Variable cost uses the recommended-sheet VOM. Current HOPE generic storage setup uses 4-hour storage. | V20: 2 | W20: =IF(COUNT(C20:F20)=4,"YES","NO") -> YES | X20: =IF(F20="","FOM needed","Ready") -> Ready
A21: Battery | B21: 1 | C21: =IF(F21="","",Recommended_CEM_Base!N11*1000) -> 142527.95 | D21: =Recommended_CEM_Base!I11 -> 0 | E21: =Recommended_CEM_Base!K11 -> 997.57593 | F21: =IF(Recommended_CEM_Base!M11="","",Recommended_CEM_Base!M11) -> 32.999473 | G21: =Recommended_CEM_Base!C11 -> 0.07 | H21: =Recommended_CEM_Base!E11 -> 0.10979462 | I21: =Recommended_CEM_Base!B11 -> 15 | J21: 2035 | L21: 2025 | M21: 1 | N21: Recommended hybrid | O21: Battery_4h | P21: Technology-specific base | Q21: 7% real CRF | R21: 0 | S21: 0 | T21: https://github.com/swang22/PJM_DC_health_study_project/blob/main/scenario_assumptions/candidate_resource_costs_2035.csv | U21: Linked to Recommended_CEM_Base. CAPEX source = NLR 2025 Mid. Variable cost uses the recommended-sheet VOM. | V21: 4 | W21: =IF(COUNT(C21:F21)=4,"YES","NO") -> YES | X21: =IF(F21="","FOM needed","Ready") -> Ready
A22: Battery | B22: 0 | C22: =IF(F22="","",Recommended_CEM_Base!N12*1000) -> 218397.76 | D22: =Recommended_CEM_Base!I12 -> 0 | E22: =Recommended_CEM_Base!K12 -> 1576.6929 | F22: =IF(Recommended_CEM_Base!M12="","",Recommended_CEM_Base!M12) -> 45.285354 | G22: =Recommended_CEM_Base!C12 -> 0.07 | H22: =Recommended_CEM_Base!E12 -> 0.10979462 | I22: =Recommended_CEM_Base!B12 -> 15 | J22: 2035 | L22: 2025 | M22: 1 | N22: Recommended hybrid | O22: Battery_6h | P22: Technology-specific base | Q22: 7% real CRF | R22: 0 | S22: 0 | T22: https://github.com/swang22/PJM_DC_health_study_project/blob/main/scenario_assumptions/candidate_resource_costs_2035.csv | U22: Linked to Recommended_CEM_Base. CAPEX source = ERCOT LTSA. Variable cost uses the recommended-sheet VOM. Current HOPE generic storage setup uses 4-hour storage. | V22: 6 | W22: =IF(COUNT(C22:F22)=4,"YES","NO") -> YES | X22: =IF(F22="","FOM needed","Ready") -> Ready
A23: DieselBackup | B23: 1 | C23: =Recommended_CEM_Base!H13*1000 -> 110514.34 | D23: =IF(OR(R23="",S23=""),"",Recommended_CEM_Base!I13+R23*S23) | E23: =Recommended_CEM_Base!D13 -> 800 | F23: =Recommended_CEM_Base!G13 -> 35 | G23: =Recommended_CEM_Base!C13 -> 0.07 | H23: =Recommended_CEM_Base!E13 -> 0.094392926 | I23: =Recommended_CEM_Base!B13 -> 20 | J23: 2030 | L23: 2025 | M23: 1 | N23: Recommended hybrid | O23: DieselBackup | P23: Backup-generator synthesis | Q23: 7% real CRF | S23: =Diesel_Review!F20 -> 9.5 | T23: https://www.nrel.gov/docs/fy19osti/72509.pdf | U23: Standby/resilience diesel generator. Linked to Recommended_CEM_Base backup row. Enter diesel fuel price ($/MMBtu) in column R before direct run. | W23: =IF(COUNT(C23:F23)=4,"YES","NO") -> NO | X23: =IF(OR(R23="",S23=""),"Fuel price needed","Ready") -> Fuel price needed
A24: DieselBackup | B24: 1 | C24: =Recommended_CEM_Base!N13*1000 -> 110514.34 | D24: =IF(OR(R24="",S24=""),"",Recommended_CEM_Base!I13+R24*S24) | E24: =Recommended_CEM_Base!K13 -> 800 | F24: =Recommended_CEM_Base!M13 -> 35 | G24: =Recommended_CEM_Base!C13 -> 0.07 | H24: =Recommended_CEM_Base!E13 -> 0.094392926 | I24: =Recommended_CEM_Base!B13 -> 20 | J24: 2035 | L24: 2025 | M24: 1 | N24: Recommended hybrid | O24: DieselBackup | P24: Backup-generator synthesis | Q24: 7% real CRF | S24: =Diesel_Review!F20 -> 9.5 | T24: https://www.nrel.gov/docs/fy19osti/72509.pdf | U24: Standby/resilience diesel generator. Linked to Recommended_CEM_Base backup row. Enter diesel fuel price ($/MMBtu) in column R before direct run. | W24: =IF(COUNT(C24:F24)=4,"YES","NO") -> NO | X24: =IF(OR(R24="",S24=""),"Fuel price needed","Ready") -> Fuel price needed
A25: DieselPeaker | B25: 1 | C25: =Recommended_CEM_Base!H15*1000 -> 154991.53 | D25: =IF(OR(R25="",S25=""),"",Recommended_CEM_Base!I15+R25*S25) | E25: =Recommended_CEM_Base!D15 -> 1373.8713 | F25: =Recommended_CEM_Base!G15 -> 44.276182 | G25: =Recommended_CEM_Base!C15 -> 0.07 | H25: =Recommended_CEM_Base!E15 -> 0.080586404 | I25: =Recommended_CEM_Base!B15 -> 30 | J25: 2030 | L25: 2025 | M25: 1 | N25: Recommended hybrid | O25: DieselPeaker | P25: EIA Texas utility-scale ICE | Q25: 7% real CRF | S25: =Diesel_Review!F21 -> 9.5 | T25: https://www.eia.gov/analysis/studies/powerplants/capitalcost/pdf/capital_cost_AEO2020.pdf | U25: Grid-connected diesel peaker. Linked to Recommended_CEM_Base peaker row. CAPEX uses EIA/S&L Texas 20-MW ICE benchmark; enter diesel fuel price ($/MMBtu) in column R before direct run. | W25: =IF(COUNT(C25:F25)=4,"YES","NO") -> NO | X25: =IF(OR(R25="",S25=""),"Fuel price needed","Ready") -> Fuel price needed
A26: DieselPeaker | B26: 1 | C26: =Recommended_CEM_Base!N15*1000 -> 154991.53 | D26: =IF(OR(R26="",S26=""),"",Recommended_CEM_Base!I15+R26*S26) | E26: =Recommended_CEM_Base!K15 -> 1373.8713 | F26: =Recommended_CEM_Base!M15 -> 44.276182 | G26: =Recommended_CEM_Base!C15 -> 0.07 | H26: =Recommended_CEM_Base!E15 -> 0.080586404 | I26: =Recommended_CEM_Base!B15 -> 30 | J26: 2035 | L26: 2025 | M26: 1 | N26: Recommended hybrid | O26: DieselPeaker | P26: EIA Texas utility-scale ICE | Q26: 7% real CRF | S26: =Diesel_Review!F21 -> 9.5 | T26: https://www.eia.gov/analysis/studies/powerplants/capitalcost/pdf/capital_cost_AEO2020.pdf | U26: Grid-connected diesel peaker. Linked to Recommended_CEM_Base peaker row. CAPEX uses EIA/S&L Texas 20-MW ICE benchmark; enter diesel fuel price ($/MMBtu) in column R before direct run. | W26: =IF(COUNT(C26:F26)=4,"YES","NO") -> NO | X26: =IF(OR(R26="",S26=""),"Fuel price needed","Ready") -> Fuel price needed
A27: HOPE input interpretation
A28: Current HOPE reference | B28: candidate_resource_costs_2035.csv converts CAPEX/FOM/FCR into CostDollarPerMWYr and passes CostDollarPerMWh directly into candidate data.
A29: ERCOT fixed cost | B29: This sheet is already model-formatted: CostDollarPerMWYr = (annualized CAPEX + FOM) × 1000, in $/MW-yr.
A30: Thermal variable cost | B30: Fuel is intentionally not hard-wired. Enter $/MMBtu in column R; column D computes VOM + fuel price × heat rate. DieselBackup and DieselPeaker use separate fixed-cost profiles but can share the same diesel-fuel-price scenario.
A31: Battery duration | B31: The current HOPE case uses 4-hour generic storage. 2h/6h rows are preserved as alternative ERCOT profiles and require duration-aware candidate rows.

Sheet HOPE_GenCandidate
A1: HOPE gendata_candidate.csv Template — ERCOT 2030 / 2035
A2: Columns A:Y exactly follow the current HOPE gendata_candidate.csv schema. Cost columns are linked to HOPE_CostProfiles. Yellow cells/blank fields are case-specific inputs still needed before direct execution.
A4: ProjectID | B4: Zone | C4: Pmax (MW) | D4: Pmin (MW) | E4: Cost ($/MW/yr) | F4: Cost ($/MWh) | G4: Type | H4: Flag_thermal | I4: Flag_VRE | J4: Flag_mustrun | K4: EF | L4: CC | M4: AF | N4: FOR | O4: Flag_RPS | P4: CO2_ton_MWh | Q4: SO2_lb_MWh | R4: SO2_ton_MWh | S4: NOx_lb_MWh | T4: NOx_ton_MWh | U4: HeatInput_MMBtu_MWh | V4: EmissionFactorBasis | W4: QueueStatus | X4: InServiceYear | Y4: FuelPrimary | Z4: ReadyForDirectHOPE [helper] | AA4: RemainingInputs [helper] | AB4: CostProfileRow [helper]
A5: ERCOT_NGCC_2030_GENERIC | D5: 0 | E5: =HOPE_CostProfiles!C5 -> 118649.83 | F5: =HOPE_CostProfiles!D5 | G5: NGCC | H5: 1 | I5: 0 | J5: 0 | M5: 1 | O5: 0 | U5: =HOPE_CostProfiles!S5 -> 6.226 | V5: TBD_ERCOT_emission_factors | W5: Generic ERCOT cost template; replace Zone/Pmax/reliability fields with case data | X5: 2030 | Y5: Natural Gas | Z5: =IF(AND(B5<>"",C5<>"",E5<>"",F5<>"",L5<>"",M5<>"",N5<>""),"YES","NO") -> NO | AA5: Set Zone, Pmax, CC, AF/profile, FOR; thermal rows also need fuel price and emissions. | AB5: 5
A6: ERCOT_NGCT_2030_GENERIC | D6: 0 | E6: =HOPE_CostProfiles!C6 -> 103382.28 | F6: =HOPE_CostProfiles!D6 | G6: NGCT | H6: 1 | I6: 0 | J6: 0 | M6: 1 | O6: 0 | U6: =HOPE_CostProfiles!S6 -> 9.142 | V6: TBD_ERCOT_emission_factors | W6: Generic ERCOT cost template; replace Zone/Pmax/reliability fields with case data | X6: 2030 | Y6: Natural Gas | Z6: =IF(AND(B6<>"",C6<>"",E6<>"",F6<>"",L6<>"",M6<>"",N6<>""),"YES","NO") -> NO | AA6: Set Zone, Pmax, CC, AF/profile, FOR; thermal rows also need fuel price and emissions. | AB6: 6
A7: ERCOT_ICE_2030_GENERIC | D7: 0 | E7: =HOPE_CostProfiles!C7 | F7: =HOPE_CostProfiles!D7 | G7: ICE | H7: 1 | I7: 0 | J7: 0 | M7: 1 | O7: 0 | U7: =HOPE_CostProfiles!S7 | V7: TBD_ERCOT_emission_factors | W7: Generic ERCOT cost template; replace Zone/Pmax/reliability fields with case data | X7: 2030 | Y7: Natural Gas | Z7: =IF(AND(B7<>"",C7<>"",E7<>"",F7<>"",L7<>"",M7<>"",N7<>""),"YES","NO") -> NO | AA7: Set Zone, Pmax, CC, AF/profile, FOR; thermal rows also need fuel price and emissions. | AB7: 7
A8: ERCOT_NuC_2030_GENERIC | D8: 0 | E8: =HOPE_CostProfiles!C8 -> 740795.07 | F8: =HOPE_CostProfiles!D8 | G8: NuC | H8: 0 | I8: 0 | J8: 0 | K8: 0 | M8: 1 | O8: 0 | P8: 0 | Q8: 0 | R8: 0 | S8: 0 | T8: 0 | U8: 0 | V8: zero_direct_operational_emissions | W8: Generic ERCOT cost template; replace Zone/Pmax/reliability fields with case data | X8: 2030 | Y8: Nuclear | Z8: =IF(AND(B8<>"",C8<>"",E8<>"",F8<>"",L8<>"",M8<>"",N8<>""),"YES","NO") -> NO | AA8: Set Zone, Pmax, CC, FOR; confirm nuclear variable cost/fuel treatment. | AB8: 8
A9: ERCOT_WindOn_2030_GENERIC | D9: 0 | E9: =HOPE_CostProfiles!C9 -> 157009.2 | F9: =HOPE_CostProfiles!D9 -> 0 | G9: WindOn | H9: 0 | I9: 1 | J9: 0 | K9: 0 | O9: 1 | P9: 0 | Q9: 0 | R9: 0 | S9: 0 | T9: 0 | U9: 0 | V9: zero_direct_operational_emissions | W9: Generic ERCOT cost template; replace Zone/Pmax/reliability fields with case data | X9: 2030 | Y9: Wind | Z9: =IF(AND(B9<>"",C9<>"",E9<>"",F9<>"",L9<>"",M9<>"",N9<>""),"YES","NO") -> NO | AA9: Set Zone, Pmax, CC, AF/profile, FOR. | AB9: 9
A10: ERCOT_SolarPV_2030_GENERIC | D10: 0 | E10: =HOPE_CostProfiles!C10 -> 117995.32 | F10: =HOPE_CostProfiles!D10 -> 0 | G10: SolarPV | H10: 0 | I10: 1 | J10: 0 | K10: 0 | O10: 1 | P10: 0 | Q10: 0 | R10: 0 | S10: 0 | T10: 0 | U10: 0 | V10: zero_direct_operational_emissions | W10: Generic ERCOT cost template; replace Zone/Pmax/reliability fields with case data | X10: 2030 | Y10: Solar | Z10: =IF(AND(B10<>"",C10<>"",E10<>"",F10<>"",L10<>"",M10<>"",N10<>""),"YES","NO") -> NO | AA10: Set Zone, Pmax, CC, AF/profile, FOR. | AB10: 10
A11: ERCOT_NGCC_2035_GENERIC | D11: 0 | E11: =HOPE_CostProfiles!C14 -> 113754.57 | F11: =HOPE_CostProfiles!D14 | G11: NGCC | H11: 1 | I11: 0 | J11: 0 | M11: 1 | O11: 0 | U11: =HOPE_CostProfiles!S14 -> 6.226 | V11: TBD_ERCOT_emission_factors | W11: Generic ERCOT cost template; replace Zone/Pmax/reliability fields with case data | X11: 2035 | Y11: Natural Gas | Z11: =IF(AND(B11<>"",C11<>"",E11<>"",F11<>"",L11<>"",M11<>"",N11<>""),"YES","NO") -> NO | AA11: Set Zone, Pmax, CC, AF/profile, FOR; thermal rows also need fuel price and emissions. | AB11: 14
A12: ERCOT_NGCT_2035_GENERIC | D12: 0 | E12: =HOPE_CostProfiles!C15 -> 96575.793 | F12: =HOPE_CostProfiles!D15 | G12: NGCT | H12: 1 | I12: 0 | J12: 0 | M12: 1 | O12: 0 | U12: =HOPE_CostProfiles!S15 -> 9.142 | V12: TBD_ERCOT_emission_factors | W12: Generic ERCOT cost template; replace Zone/Pmax/reliability fields with case data | X12: 2035 | Y12: Natural Gas | Z12: =IF(AND(B12<>"",C12<>"",E12<>"",F12<>"",L12<>"",M12<>"",N12<>""),"YES","NO") -> NO | AA12: Set Zone, Pmax, CC, AF/profile, FOR; thermal rows also need fuel price and emissions. | AB12: 15
A13: ERCOT_ICE_2035_GENERIC | D13: 0 | E13: =HOPE_CostProfiles!C16 | F13: =HOPE_CostProfiles!D16 | G13: ICE | H13: 1 | I13: 0 | J13: 0 | M13: 1 | O13: 0 | U13: =HOPE_CostProfiles!S16 | V13: TBD_ERCOT_emission_factors | W13: Generic ERCOT cost template; replace Zone/Pmax/reliability fields with case data | X13: 2035 | Y13: Natural Gas | Z13: =IF(AND(B13<>"",C13<>"",E13<>"",F13<>"",L13<>"",M13<>"",N13<>""),"YES","NO") -> NO | AA13: Set Zone, Pmax, CC, AF/profile, FOR; thermal rows also need fuel price and emissions. | AB13: 16
A14: ERCOT_NuC_2035_GENERIC | D14: 0 | E14: =HOPE_CostProfiles!C17 -> 706973.15 | F14: =HOPE_CostProfiles!D17 | G14: NuC | H14: 0 | I14: 0 | J14: 0 | K14: 0 | M14: 1 | O14: 0 | P14: 0 | Q14: 0 | R14: 0 | S14: 0 | T14: 0 | U14: 0 | V14: zero_direct_operational_emissions | W14: Generic ERCOT cost template; replace Zone/Pmax/reliability fields with case data | X14: 2035 | Y14: Nuclear | Z14: =IF(AND(B14<>"",C14<>"",E14<>"",F14<>"",L14<>"",M14<>"",N14<>""),"YES","NO") -> NO | AA14: Set Zone, Pmax, CC, FOR; confirm nuclear variable cost/fuel treatment. | AB14: 17
A15: ERCOT_WindOn_2035_GENERIC | D15: 0 | E15: =HOPE_CostProfiles!C18 -> 149411.61 | F15: =HOPE_CostProfiles!D18 -> 0 | G15: WindOn | H15: 0 | I15: 1 | J15: 0 | K15: 0 | O15: 1 | P15: 0 | Q15: 0 | R15: 0 | S15: 0 | T15: 0 | U15: 0 | V15: zero_direct_operational_emissions | W15: Generic ERCOT cost template; replace Zone/Pmax/reliability fields with case data | X15: 2035 | Y15: Wind | Z15: =IF(AND(B15<>"",C15<>"",E15<>"",F15<>"",L15<>"",M15<>"",N15<>""),"YES","NO") -> NO | AA15: Set Zone, Pmax, CC, AF/profile, FOR. | AB15: 18
A16: ERCOT_SolarPV_2035_GENERIC | D16: 0 | E16: =HOPE_CostProfiles!C19 -> 108393.11 | F16: =HOPE_CostProfiles!D19 -> 0 | G16: SolarPV | H16: 0 | I16: 1 | J16: 0 | K16: 0 | O16: 1 | P16: 0 | Q16: 0 | R16: 0 | S16: 0 | T16: 0 | U16: 0 | V16: zero_direct_operational_emissions | W16: Generic ERCOT cost template; replace Zone/Pmax/reliability fields with case data | X16: 2035 | Y16: Solar | Z16: =IF(AND(B16<>"",C16<>"",E16<>"",F16<>"",L16<>"",M16<>"",N16<>""),"YES","NO") -> NO | AA16: Set Zone, Pmax, CC, AF/profile, FOR. | AB16: 19
A17: ERCOT_DIESEL_BACKUP_2030_GENERIC | D17: 0 | E17: =HOPE_CostProfiles!C23 -> 110514.34 | F17: =IF(HOPE_CostProfiles!D23="","",HOPE_CostProfiles!D23) | G17: DieselBackup | H17: 1 | I17: 0 | J17: 0 | K17: 0.7763875 | M17: 1 | O17: 0 | P17: 0.7763875 | U17: 9.5 | V17: EIA distillate CO2 factor; standby diesel; SO2/NOx TBD by selected genset/emissions controls | W17: Generic ERCOT backup-diesel template; intended for standby/resilience use | X17: 2030 | Y17: Diesel | Z17: =IF(AND(B17<>"",C17<>"",E17<>"",F17<>"",L17<>"",M17<>"",N17<>""),"YES","NO") -> NO | AA17: Set Zone, Pmax, CC, FOR and diesel fuel price; backup generator is distinct from utility-scale peaker. | AB17: 23
A18: ERCOT_DIESEL_BACKUP_2035_GENERIC | D18: 0 | E18: =HOPE_CostProfiles!C24 -> 110514.34 | F18: =IF(HOPE_CostProfiles!D24="","",HOPE_CostProfiles!D24) | G18: DieselBackup | H18: 1 | I18: 0 | J18: 0 | K18: 0.7763875 | M18: 1 | O18: 0 | P18: 0.7763875 | U18: 9.5 | V18: EIA distillate CO2 factor; standby diesel; SO2/NOx TBD by selected genset/emissions controls | W18: Generic ERCOT backup-diesel template; intended for standby/resilience use | X18: 2035 | Y18: Diesel | Z18: =IF(AND(B18<>"",C18<>"",E18<>"",F18<>"",L18<>"",M18<>"",N18<>""),"YES","NO") -> NO | AA18: Set Zone, Pmax, CC, FOR and diesel fuel price; backup generator is distinct from utility-scale peaker. | AB18: 24
A19: ERCOT_DIESEL_PEAKER_2030_GENERIC | D19: 0 | E19: =HOPE_CostProfiles!C25 -> 154991.53 | F19: =IF(HOPE_CostProfiles!D25="","",HOPE_CostProfiles!D25) | G19: DieselPeaker | H19: 1 | I19: 0 | J19: 0 | K19: 0.7763875 | M19: 1 | O19: 0 | P19: 0.7763875 | U19: 9.5 | V19: EIA distillate CO2 factor; utility-scale peaker; SO2/NOx TBD by engine/emissions-control configuration | W19: Generic ERCOT utility-scale diesel peaker template; cost basis from EIA/S&L Texas 20-MW ICE benchmark | X19: 2030 | Y19: Diesel | Z19: =IF(AND(B19<>"",C19<>"",E19<>"",F19<>"",L19<>"",M19<>"",N19<>""),"YES","NO") -> NO | AA19: Set Zone, Pmax, CC, FOR and diesel fuel price; confirm SO2/NOx factors for selected peaker configuration. | AB19: 25
A20: ERCOT_DIESEL_PEAKER_2035_GENERIC | D20: 0 | E20: =HOPE_CostProfiles!C26 -> 154991.53 | F20: =IF(HOPE_CostProfiles!D26="","",HOPE_CostProfiles!D26) | G20: DieselPeaker | H20: 1 | I20: 0 | J20: 0 | K20: 0.7763875 | M20: 1 | O20: 0 | P20: 0.7763875 | U20: 9.5 | V20: EIA distillate CO2 factor; utility-scale peaker; SO2/NOx TBD by engine/emissions-control configuration | W20: Generic ERCOT utility-scale diesel peaker template; cost basis from EIA/S&L Texas 20-MW ICE benchmark | X20: 2035 | Y20: Diesel | Z20: =IF(AND(B20<>"",C20<>"",E20<>"",F20<>"",L20<>"",M20<>"",N20<>""),"YES","NO") -> NO | AA20: Set Zone, Pmax, CC, FOR and diesel fuel price; confirm SO2/NOx factors for selected peaker configuration. | AB20: 26

Sheet HOPE_StorageCandidate
A1: HOPE storagedata_candidate.csv Template — ERCOT Battery Candidates
A2: Columns A:V exactly follow the current HOPE storagedata_candidate.csv schema. Enter Zone and Max Power; Capacity (MWh) will calculate automatically from the helper duration.
A4: ProjectID | B4: Zone | C4: Type | D4: Capacity (MWh) | E4: Max Power (MW) | F4: Charging efficiency | G4: Discharging efficiency | H4: Cost ($/MW/yr) | I4: Cost ($/MWh) | J4: EF | K4: CO2_ton_MWh | L4: SO2_lb_MWh | M4: SO2_ton_MWh | N4: NOx_lb_MWh | O4: NOx_ton_MWh | P4: HeatInput_MMBtu_MWh | Q4: EmissionFactorBasis | R4: CC | S4: Charging Rate | T4: Discharging Rate | U4: QueueStatus | V4: InServiceYear | W4: DurationHours [helper] | X4: ReadyForDirectHOPE [helper] | Y4: RemainingInputs [helper]
A5: ERCOT_BATTERY_2H_2030_GENERIC | C5: Battery | D5: =IF(E5="","",E5*W5) | F5: 0.85 | G5: 1 | H5: =HOPE_CostProfiles!C11 -> 98856.342 | I5: =HOPE_CostProfiles!D11 -> 0 | J5: 0 | K5: 0 | L5: 0 | M5: 0 | N5: 0 | O5: 0 | P5: 0 | Q5: generic_storage_zero_direct_emissions | S5: 1 | T5: 1 | U5: Generic ERCOT storage cost template | V5: 2030 | W5: 2 | X5: =IF(AND(B5<>"",E5<>"",H5<>"",I5<>"",R5<>""),"YES","NO") -> NO | Y5: Set Zone, Max Power/build limit, and ERCOT capacity credit (CC).
A6: ERCOT_BATTERY_4H_2030_GENERIC | C6: Battery | D6: =IF(E6="","",E6*W6) | F6: 0.85 | G6: 1 | H6: =HOPE_CostProfiles!C12 -> 161511.61 | I6: =HOPE_CostProfiles!D12 -> 0 | J6: 0 | K6: 0 | L6: 0 | M6: 0 | N6: 0 | O6: 0 | P6: 0 | Q6: generic_storage_zero_direct_emissions | S6: 1 | T6: 1 | U6: Generic ERCOT storage cost template | V6: 2030 | W6: 4 | X6: =IF(AND(B6<>"",E6<>"",H6<>"",I6<>"",R6<>""),"YES","NO") -> NO | Y6: Set Zone, Max Power/build limit, and ERCOT capacity credit (CC).
A7: ERCOT_BATTERY_6H_2030_GENERIC | C7: Battery | D7: =IF(E7="","",E7*W7) | F7: 0.85 | G7: 1 | H7: =HOPE_CostProfiles!C13 -> 236471.95 | I7: =HOPE_CostProfiles!D13 -> 0 | J7: 0 | K7: 0 | L7: 0 | M7: 0 | N7: 0 | O7: 0 | P7: 0 | Q7: generic_storage_zero_direct_emissions | S7: 1 | T7: 1 | U7: Generic ERCOT storage cost template | V7: 2030 | W7: 6 | X7: =IF(AND(B7<>"",E7<>"",H7<>"",I7<>"",R7<>""),"YES","NO") -> NO | Y7: Set Zone, Max Power/build limit, and ERCOT capacity credit (CC).
A8: ERCOT_BATTERY_2H_2035_GENERIC | C8: Battery | D8: =IF(E8="","",E8*W8) | F8: 0.85 | G8: 1 | H8: =HOPE_CostProfiles!C20 -> 91548.361 | I8: =HOPE_CostProfiles!D20 -> 0 | J8: 0 | K8: 0 | L8: 0 | M8: 0 | N8: 0 | O8: 0 | P8: 0 | Q8: generic_storage_zero_direct_emissions | S8: 1 | T8: 1 | U8: Generic ERCOT storage cost template | V8: 2035 | W8: 2 | X8: =IF(AND(B8<>"",E8<>"",H8<>"",I8<>"",R8<>""),"YES","NO") -> NO | Y8: Set Zone, Max Power/build limit, and ERCOT capacity credit (CC).
A9: ERCOT_BATTERY_4H_2035_GENERIC | C9: Battery | D9: =IF(E9="","",E9*W9) | F9: 0.85 | G9: 1 | H9: =HOPE_CostProfiles!C21 -> 142527.95 | I9: =HOPE_CostProfiles!D21 -> 0 | J9: 0 | K9: 0 | L9: 0 | M9: 0 | N9: 0 | O9: 0 | P9: 0 | Q9: generic_storage_zero_direct_emissions | S9: 1 | T9: 1 | U9: Generic ERCOT storage cost template | V9: 2035 | W9: 4 | X9: =IF(AND(B9<>"",E9<>"",H9<>"",I9<>"",R9<>""),"YES","NO") -> NO | Y9: Set Zone, Max Power/build limit, and ERCOT capacity credit (CC).
A10: ERCOT_BATTERY_6H_2035_GENERIC | C10: Battery | D10: =IF(E10="","",E10*W10) | F10: 0.85 | G10: 1 | H10: =HOPE_CostProfiles!C22 -> 218397.76 | I10: =HOPE_CostProfiles!D22 -> 0 | J10: 0 | K10: 0 | L10: 0 | M10: 0 | N10: 0 | O10: 0 | P10: 0 | Q10: generic_storage_zero_direct_emissions | S10: 1 | T10: 1 | U10: Generic ERCOT storage cost template | V10: 2035 | W10: 6 | X10: =IF(AND(B10<>"",E10<>"",H10<>"",I10<>"",R10<>""),"YES","NO") -> NO | Y10: Set Zone, Max Power/build limit, and ERCOT capacity credit (CC).

Sheet Diesel_Review
A1: Diesel Technology Cost Review — Backup Generator vs. Utility-Scale Peaker
A2: Diesel is split into two applications: a smaller standby/backup generator and a grid-connected utility-scale peaker plant. Both are separate from ERCOT's natural-gas ICE category. Mature-technology CAPEX is held constant in real 2025 dollars for 2030 and 2035.
A4: Source | B4: Context | C4: Raw dollar year | D4: Raw CAPEX low ($/kW) | E4: Raw CAPEX high ($/kW) | F4: Raw FOM ($/kW-yr) | G4: Raw maintenance / other | H4: Lifetime (yr) | I4: CPI factor to 2025$ | J4: 2025$ CAPEX low | K4: 2025$ CAPEX high | L4: 2025$ FOM | M4: Use / interpretation | N4: URL
A5: MIT Future of Energy Storage (2022) | B5: Reference diesel generator in capacity-expansion/resilience analysis | C5: 2018 | D5: 400 | E5: 400 | F5: 100 | I5: =C14 -> 1.2820949 | J5: =D5*I5 -> 512.83795 | K5: =E5*I5 -> 512.83795 | L5: =IF(F5="","",F5*I5) -> 128.20949 | M5: Useful lower-CAPEX cross-check; MIT keeps diesel CAPEX flat in real 2018$ through 2030. | N5: https://energy.mit.edu/wp-content/uploads/2022/05/The-Future-of-Energy-Storage.pdf
A6: NREL backup generator study (2019) | B6: 500-kW diesel standby generator | C6: 2019 | D6: 800 | E6: 800 | G6: $405/kW life-cycle non-fuel maintenance | H6: 20 | I6: =C15 -> 1.2592771 | J6: =D6*I6 -> 1007.4217 | K6: =E6*I6 -> 1007.4217 | L6: =IF(F6="","",F6*I6) | M6: Primary lifetime/capital-cost benchmark. Dollar year is not explicit; 2019 report year is used only for normalization. | N6: https://www.nrel.gov/docs/fy19osti/72509.pdf
A7: EDF Power Resiliency (2024) | B7: Example average backup power system cost | C7: 2024 | D7: 800 | E7: 800 | F7: 35 | I7: =C16 -> 1.0263127 | J7: =D7*I7 -> 821.05015 | K7: =E7*I7 -> 821.05015 | L7: =IF(F7="","",F7*I7) -> 35.920944 | M7: Contemporary synthesis: $800/kW upfront and $35/kW-yr non-fuel annual operating cost. | N7: https://www.edf.org/sites/default/files/2024-04/Power-Resiliency-Electric-Fleets.pdf
A8: BofA data-center generator review (2024) | B8: Large data-center diesel backup system | C8: 2024 | D8: 600 | E8: 900 | G8: $300-450/kW genset + $300-450/kW tank/pump/installation | I8: =C16 -> 1.0263127 | J8: =D8*I8 -> 615.78761 | K8: =E8*I8 -> 923.68142 | L8: =IF(F8="","",F8*I8) | M8: Current installed-cost market check; supports roughly $600-900/kW total system cost. | N8: https://d28lcup14p4e72.cloudfront.net/273862/8991641/BofA%20-%20Who%20Makes%20the%20Data%20Center.pdf
A9: EIA generator construction costs (2024) | B9: Observed petroleum-liquids generators installed in 2024; small national sample | C9: 2024 | D9: 1066 | E9: 1066 | G9: Capacity-weighted average; 33 MW total petroleum-liquids additions in reported sample | I9: =C16 -> 1.0263127 | J9: =D9*I9 -> 1094.0493 | K9: =E9*I9 -> 1094.0493 | L9: =IF(F9="","",F9*I9) | M9: Current empirical lower-cost check for grid-scale liquid-fuel generation; sample is small and not ERCOT-specific. | N9: https://www.eia.gov/electricity/generatorcosts/
A10: EIA / Sargent & Lundy AEO2020 capital-cost study | B10: 20-MW internal-combustion-engine plant; location-adjustment table explicitly covers natural gas or oil-fired diesel; Texas Houston | C10: 2019 | D10: 1091 | E10: 1091 | F10: 35.16 | G10: VOM = $5.69/MWh (2019$); operating life = 30 yr. Detailed Case 4 gas-engine heat rate = 8.295 MMBtu/MWh. | H10: 30 | I10: =C15 -> 1.2592771 | J10: =D10*I10 -> 1373.8713 | K10: =E10*I10 -> 1373.8713 | L10: =IF(F10="","",F10*I10) -> 44.276182 | M10: Primary grid-scale peaker CAPEX benchmark for Texas. Non-fuel O&M is used as an engine-plant proxy; diesel heat rate remains separately assumed at 9.5 MMBtu/MWh. | N10: https://www.eia.gov/analysis/studies/powerplants/capitalcost/pdf/capital_cost_AEO2020.pdf
A13: CPI year | B13: Annual CPI-U | C13: CPI factor to 2025$ | D13: Source
A14: 2018 | B14: 251.107 | C14: =$B$17/B14 -> 1.2820949 | D14: https://www.bls.gov/regions/northeast/data/consumerpriceindex_us_table.htm
A15: 2019 | B15: 255.657 | C15: =$B$17/B15 -> 1.2592771 | D15: https://www.bls.gov/regions/northeast/data/consumerpriceindex_us_table.htm
A16: 2024 | B16: 313.689 | C16: =$B$17/B16 -> 1.0263127 | D16: https://www.bls.gov/regions/northeast/data/consumerpriceindex_us_table.htm
A17: 2025 | B17: 321.943 | C17: 1 | D17: https://www.bls.gov/regions/northeast/data/consumerpriceindex_us_table.htm
A18: Recommended diesel assumption for ERCOT CEM
A19: Technology | B19: 2030 CAPEX (2025$/kW) | C19: 2035 CAPEX (2025$/kW) | D19: FOM (2025$/kW-yr) | E19: VOM excl. fuel (2025$/MWh) | F19: Heat rate (MMBtu/MWh) | G19: Economic life (yr) | H19: Real WACC | I19: Low CAPEX | J19: Base CAPEX | K19: High CAPEX | L19: Real-cost trajectory | M19: Fuel treatment | N19: Rationale
A20: Diesel backup generator | B20: 800 | C20: 800 | D20: 35 | E20: 0 | F20: 9.5 | G20: 20 | H20: 0.07 | I20: 600 | J20: 800 | K20: 1000 | L20: Flat in real 2025$ through 2035 | M20: Fuel price kept separate and editable in HOPE; variable cost = fuel price × heat rate + VOM. | N20: Backup/standby case. Base is a rounded synthesis of NREL/EDF and current data-center installed-cost evidence; intended for resilience/standby use rather than a utility-scale peaker plant.
A21: Diesel peaker plant | B21: =J10 -> 1373.8713 | C21: =J10 -> 1373.8713 | D21: =L10 -> 44.276182 | E21: =5.69*I10 -> 7.1652866 | F21: 9.5 | G21: 30 | H21: 0.07 | I21: =J9 -> 1094.0493 | J21: =J10 -> 1373.8713 | K21: =J21*1.25 -> 1717.3391 | L21: Flat in real 2025$ through 2035 | M21: Fuel price kept separate and editable in HOPE; variable cost = fuel price × heat rate + VOM. | N21: Grid-connected peaker case. Base CAPEX uses the EIA/S&L Texas-Houston 20-MW ICE location benchmark converted from 2019$ to 2025$. FOM/VOM use the same EIA engine-plant non-fuel O&M as a proxy; diesel heat rate is kept at 9.5 MMBtu/MWh.
A23: Performance and emissions cross-check
A24: Heat rate | B24: 9.5 | C24: MMBtu/MWh | M24: Rounded from a 1.25-MW data-center diesel example consuming ~86 gal/h; close to the ~10 MMBtu/MWh conventional diesel-engine benchmark. | N24: https://d28lcup14p4e72.cloudfront.net/273862/8991641/BofA%20-%20Who%20Makes%20the%20Data%20Center.pdf
A25: CO2 factor | B25: 163.45 | C25: lb CO2/MMBtu | M25: EIA factor for diesel/distillate fuel oil. | N25: https://www.eia.gov/environment/emissions/co2_vol_mass.php
A26: CO2 intensity | B26: =B24*B25/2000 -> 0.7763875 | C26: ton CO2/MWh | M26: Calculated from recommended heat rate × EIA diesel CO2 factor / 2,000. | N26: https://www.eia.gov/environment/emissions/co2_vol_mass.php
